Global/global_std_def.v
`ifndef __GLOBAL_STD_DEF__
    `define __GLOBAL_STD_DEF__

    /*  singal level  */
    `define HIGH        1'b1
    `define LOW         1'b0

    /*  enable & disable  */
    `define DISABLE     1'b0
    `define ENABLE      1'b1
    `define DISABLE_    1'b1
    `define ENABLE_     1'b0

    /*  read & write  */
    `define READ        1'b1
    `define WRITE       1'b0

    /*  Least Significant Bit  */
    `define LSB         0

    /*  byte data  */
    `define BYTE_DATA_WIDTH     8
    `define BYTE_MSB            (`BYTE_DATA_WIDTH-1)
    `define BYTE_DATA_BUS       `BYTE_MSB:`LSB

    /*  word data  */
    `define WORD_DATA_WIDTH     32
    `define WORD_MSB            (`WORD_DATA_WIDTH-1)
    `define WORD_DATA_BUS       `WORD_MSB:`LSB

    /*  word address  */
    `define WORD_ADDR_WIDTH     30
    `define WORD_ADDR_MSB       (`WORD_ADDR_WIDTH-1)
    `define WORD_ADDR_BUS       `WORD_ADDR_MSB:`LSB

    /*  address offset  */
    `define BYTE_OFFSET_WIDTH   2
    `define BYTE_OFFSET_MSB     (`BYTE_OFFSET_WIDTH-1)
    `define BYTE_OFFSET_BUS     `BYTE_OFFSET_MSB:`LSB

    /*  address location  */
    `define WORD_ADDR_LOC       `WORD_ADDR_MSB:`BYTE_OFFSET_WIDTH
    `define BYTE_OFFSET_LOC     `BYTE_OFFSET_MSB:`LSB
    `define BYTE_OFFSET_WORD    2'b00

`endif

Global/global_cfg_def.v
`ifndef __GLOBAL_CFG_DEF__
    `define __GLOBAL_CFG_DEF__

    /*  choose RESET polarity  */
    // `define POSITIVE_RESET
    `define NEGATIVE_RESET

    /*  choose MEMORY polarity  */
    `define POSITIVE_MEMORY
    // `define NEGATIVE_MRMORY

    /*  Enable I/O Modules  */
    // `define IMPLEMENT_TIMER
    // `define IMPLEMENT_UART
    // `define IMPLEMENT_GPIO

    /*  generate RESET_ENABLE & RESET_DISABLE & RESET_EDGE */
    // book is wrong???
    // `ifdef POSITIVE_RESET
    //     `define RESET_EDGE      posedge
    //     `define RESET_ENABLE    1'b0
    //     `define RESET_DISABLE   1'b1
    // `elif NEGATIVE_RESET
        `define RESET_EDGE      negedge
        `define RESET_ENABLE    1'b1
        `define RESET_DISABLE   1'b0
    // `endif
    

    /*  generate MEM_ENABLE & MEM_DISABLE  */
    // `ifdef POSITIVE_MEMORY
        `define MEM_ENABLE    1'b1
        `define MEM_DISABLE   1'b0
    // `elif NEGATIVE_MRMORY
    //     `define MEM_ENABLE    1'b0
    //     `define MEM_DISABLE   1'b1
    // `endif

`endif

CPU/cpu_def.v
`ifndef __CPU_DEF__
    `define __CPU_DEF__

        `include "./Global/global_std_def.v"

        /*  Register  */
        `define REG_NUM         32
        `define REG_ADDR_WIDTH  5
        `define REG_ADDR_BUS    (`REG_ADDR_WIDTH-1):`LSB

        /*  IRQ Channel  */
        `define CPU_IRQ_CH      8

        /*  ALU OP Bus  */
        `define ALU_OP_WIDTH    4
        `define ALU_OP_BUS      (`ALU_OP_WIDTH-1):`LSB

        /*  ALU OP  */
        `define ALU_OP_NOP      4'h0
        `define ALU_OP_AND      4'h1
        `define ALU_OP_OR       4'h2
        `define ALU_OP_XOR      4'h3
        `define ALU_OP_ADDS     4'h4
        `define ALU_OP_ADDU     4'h5
        `define ALU_OP_SUBS     4'h6
        `define ALU_OP_SUBU     4'h7
        `define ALU_OP_SHRL     4'h8
        `define ALU_OP_SHLL     4'h9

        /*  MEM OP Bus  */
        `define MEM_OP_WIDTH    2
        `define MEM_OP_BUS      (`MEM_OP_WIDTH-1):`LSB

        /*  MEM OP  */
        `define MEM_OP_NOP      2'h0
        `define MEM_OP_LDW      2'h1
        `define MEM_OP_STW      2'h2

        /*  CTRL OP Bus  */
        `define CTRL_OP_WIDTH   2
        `define CTRL_OP_BUS     (`CTRL_OP_WIDTH-1):`LSB

        /*  CTRL OP  */
        `define CTRL_OP_NOP     2'h0
        `define CTRL_OP_WRCR    2'h1
        `define CTRL_OP_EXRT    2'h2

        /*  CPU EXE Mode Bus  */
        `define CPU_EXE_MODE_WIDTH  1
        `define CPU_EXE_MODE_BUS    (`CPU_EXE_MODE_WIDTH-1):`LSB

        /*  CPU EXE Mode  */
        `define CPU_KERNEL_MODE     1'b0
        `define CPU_USER_MODE       1'b1

        /*  CREG ADDR  */
        `define CREG_ADDR_STATUS        5'h0
        `define CREG_ADDR_RRE_STATUS    5'h1
        `define CREG_ADDR_PC            5'h2
        `define CREG_ADDR_EPC           5'h3
        `define CREG_ADDR_EXP_VECTOR    5'h4
        `define CREG_ADDR_CAUSE         5'h5
        `define CREG_ADDR_INT_MASK      5'h6
        `define CREG_ADDR_IRQ           5'h7

        `define CREG_ADDR_ROM_SIZE      5'h1d
        `define CREG_ADDR_SPM_SIZE      5'h1e
        `define CREG_ADDR_CPU_INFO      5'h1f

        /*  CREG Loc  */
        `define CREG_EXE_MODE_LOC       0
        `define CREG_INT_ENABLE_LOC     1
        `define CREG_EXP_CODE_LOC       2:0
        `define CREG_DLY_FLAG_LOC       3

        /*  BUS IF State Bus  */
        `define BUS_IF_STATE_BUS        1:`LSB

        /*  BUS IF State  */
        `define BUS_IF_STATE_IDLE       2'h0
        `define BUS_IF_STATE_REQ        2'h1
        `define BUS_IF_STATE_ACCESS     2'h2
        `define BUS_IF_STATE_STALL      2'h3

        /*  ???  */
        `define RESET_VECTOR            30'h0
        `define SH_AMOUNT_BUS           4:0
        `define SH_AMOUNT_LOC           4:0

        /*  Release  */
        `define RELEASE_YEAR            8'd41
        `define RELEASE_MONTH           8'd7
        `define RELEASE_VERSION         8'd1
        `define RELEASE_REVISION        8'd0

`endif

CPU/cpu_gpr.v
`include "./CPU/cpu_def.v"
`include "./Global/global_cfg_def.v"
`include "./Global/global_std_def.v"

/*  General Register  */
module cpu_gpr(
    /*  clk & reset  */
    input wire clk,
    input wire reset,

    /*  read port 0-1  */
    input wire [`REG_ADDR_BUS] rd_addr_0,
    output wire [`WORD_DATA_BUS] rd_data_0,
    
    input wire [`REG_ADDR_BUS] rd_addr_1,
    output wire [`WORD_DATA_BUS] rd_data_1,

    /*  write port  */
    input wire we_n,
    input wire [`REG_ADDR_BUS] wr_addr,     //book is wrong???
    input wire [`WORD_DATA_BUS] wr_data
);

    reg [`WORD_DATA_BUS] gpr [(`REG_NUM-1):0];
    integer i;

    /*  Write After Read  */
    /*  Read  */
    assign rd_data_0 = ((we_n == `ENABLE_) && (wr_addr == rd_addr_0)) ? wr_data : gpr[rd_addr_0];
    assign rd_data_1 = ((we_n == `ENABLE_) && (wr_addr == rd_addr_1)) ? wr_data : gpr[rd_addr_1];

    /*  Write  */
    always @(posedge clk or `RESET_EDGE reset)
    begin
        if(reset == `RESET_ENABLE)
        begin
            /*  Reset  */
            for(i=0; i<`REG_NUM; i=i+1)
            begin
                gpr[i] <= #1 `WORD_DATA_WIDTH'h0;
            end
        end
        else
        begin
            /*  Write  */
            if(we_n == `ENABLE_)
            begin
                gpr[wr_addr] <= #1 wr_data;
            end
        end
    end

endmodule // cpu_gpr

CPU/testbench/cpu_gpr_tb.v
`timescale 1ns/100ps

`include "./CPU/cpu_gpr.v"
`include "./Global/global_std_def.v"


module cpu_gpr_tb;

    /*  clk & reset  */
    reg clk = `LOW;
    reg reset = `RESET_ENABLE;

    /*  read port 0-1  */
    reg [`REG_ADDR_BUS] rd_addr_0;
    wire [`WORD_DATA_BUS] rd_data_0;

    reg [`REG_ADDR_BUS] rd_addr_1;
    wire [`WORD_DATA_BUS] rd_data_1;

    /*  write port  */
    reg we_n = `DISABLE_;
    reg [`REG_ADDR_BUS] wr_addr;
    reg [`WORD_DATA_BUS] wr_data;


    /*  Instance  */
    cpu_gpr cpu_gpr_01(
        /*  clk & reset  */
        clk,
        reset,

        /*  read port 0-1  */
        rd_addr_0,
        rd_data_0,
    
        rd_addr_1,
        rd_data_1,

        /*  write port  */
        we_n,
        wr_addr,
        wr_data
    );

    /*  clock  */
    always
        #10 clk = ~clk;

    /*  testbench  */
    initial
    begin
        $dumpfile("cpu_gpr.vcd");
        $dumpvars(0,cpu_gpr_tb);
        
        #50 reset = `RESET_DISABLE;
        
        // test we_n
        #50 wr_addr = `REG_ADDR_WIDTH'h0;
        wr_data = `WORD_DATA_WIDTH'hAAAA;
        we_n = `DISABLE_;
        rd_addr_0 = `REG_ADDR_WIDTH'h0;

        // write + read0
        #50 wr_addr = `REG_ADDR_WIDTH'h1;
        wr_data = `WORD_DATA_WIDTH'h1234;
        we_n = `ENABLE_;

        #50 rd_addr_0 = `REG_ADDR_WIDTH'h1;
        #50 we_n = `DISABLE_;

        // write + read1
        #50 wr_addr = `REG_ADDR_WIDTH'h2;
        wr_data = `WORD_DATA_WIDTH'h5678;
        we_n = `ENABLE_;

        #50 we_n = `DISABLE_;
        #50 rd_addr_1 = `REG_ADDR_WIDTH'h2;

        // test reset
        #50 reset = `RESET_ENABLE;
        #50 reset = `RESET_DISABLE;

        #50 rd_addr_0 = `REG_ADDR_WIDTH'h2;
        rd_addr_1 = `REG_ADDR_WIDTH'h1;


        #100 $finish;
    end

endmodule // cpu_gpr_tb

CPU/testbench/cpu_gpr.vcd
$date
	Thu Nov 14 00:06:14 2019
$end
$version
	Icarus Verilog
$end
$timescale
	100ps
$end
$scope module cpu_gpr_tb $end
$var wire 32 ! rd_data_1 [31:0] $end
$var wire 32 " rd_data_0 [31:0] $end
$var reg 1 # clk $end
$var reg 5 $ rd_addr_0 [4:0] $end
$var reg 5 % rd_addr_1 [4:0] $end
$var reg 1 & reset $end
$var reg 1 ' we_n $end
$var reg 5 ( wr_addr [4:0] $end
$var reg 32 ) wr_data [31:0] $end
$scope module cpu_gpr_01 $end
$var wire 1 # clk $end
$var wire 5 * rd_addr_0 [4:0] $end
$var wire 5 + rd_addr_1 [4:0] $end
$var wire 1 & reset $end
$var wire 1 ' we_n $end
$var wire 5 , wr_addr [4:0] $end
$var wire 32 - wr_data [31:0] $end
$var wire 32 . rd_data_1 [31:0] $end
$var wire 32 / rd_data_0 [31:0] $end
$var integer 32 0 i [31:0] $end
$upscope $end
$upscope $end
$enddefinitions $end
#0
$dumpvars
bx 0
bx /
bx .
bx -
bx ,
bx +
bx *
bx )
bx (
1'
1&
bx %
bx $
0#
bx "
bx !
$end
#100
b100000 0
1#
#200
0#
#300
b100000 0
1#
#400
0#
#500
1#
0&
#600
0#
#700
1#
#800
0#
#900
1#
#1000
b0 "
b0 /
0#
b0 $
b0 *
b1010101010101010 )
b1010101010101010 -
b0 (
b0 ,
#1100
1#
#1200
0#
#1300
1#
#1400
0#
#1500
1#
0'
b1001000110100 )
b1001000110100 -
b1 (
b1 ,
#1600
0#
#1700
1#
#1800
0#
#1900
1#
#2000
b1001000110100 "
b1001000110100 /
0#
b1 $
b1 *
#2100
1#
#2200
0#
#2300
1#
#2400
0#
#2500
1#
1'
#2600
0#
#2700
1#
#2800
0#
#2900
1#
#3000
0#
0'
b101011001111000 )
b101011001111000 -
b10 (
b10 ,
#3100
1#
#3200
0#
#3300
1#
#3400
0#
#3500
1#
1'
#3600
0#
#3700
1#
#3800
0#
#3900
1#
#4000
b101011001111000 !
b101011001111000 .
0#
b10 %
b10 +
#4100
1#
#4200
0#
#4300
1#
#4400
0#
#4500
b100000 0
1#
1&
#4510
b0 !
b0 .
b0 "
b0 /
#4600
0#
#4700
b100000 0
1#
#4800
0#
#4900
b100000 0
1#
#5000
0#
0&
#5100
1#
#5200
0#
#5300
1#
#5400
0#
#5500
1#
b1 %
b1 +
b10 $
b10 *
