Global/global_cfg_def.v
`ifndef __GLOBAL_CFG_DEF__
    `define __GLOBAL_CFG_DEF__

    /*  choose RESET polarity  */
    // `define POSITIVE_RESET
    `define NEGATIVE_RESET

    /*  choose MEMORY polarity  */
    `define POSITIVE_MEMORY
    // `define NEGATIVE_MRMORY

    /*  Enable I/O Modules  */
    // `define IMPLEMENT_TIMER
    // `define IMPLEMENT_UART
    // `define IMPLEMENT_GPIO

    /*  generate RESET_ENABLE & RESET_DISABLE & RESET_EDGE */
    // book is wrong???
    // `ifdef POSITIVE_RESET
    //     `define RESET_EDGE      posedge
    //     `define RESET_ENABLE    1'b0
    //     `define RESET_DISABLE   1'b1
    // `elif NEGATIVE_RESET
        `define RESET_EDGE      negedge
        `define RESET_ENABLE    1'b1
        `define RESET_DISABLE   1'b0
    // `endif
    

    /*  generate MEM_ENABLE & MEM_DISABLE  */
    // `ifdef POSITIVE_MEMORY
        `define MEM_ENABLE    1'b1
        `define MEM_DISABLE   1'b0
    // `elif NEGATIVE_MRMORY
    //     `define MEM_ENABLE    1'b0
    //     `define MEM_DISABLE   1'b1
    // `endif

`endif

Global/global_std_def.v
`ifndef __GLOBAL_STD_DEF__
    `define __GLOBAL_STD_DEF__

    /*  singal level  */
    `define HIGH        1'b1
    `define LOW         1'b0

    /*  enable & disable  */
    `define DISABLE     1'b0
    `define ENABLE      1'b1
    `define DISABLE_    1'b1
    `define ENABLE_     1'b0

    /*  read & write  */
    `define READ        1'b1
    `define WRITE       1'b0

    /*  Least Significant Bit  */
    `define LSB         0

    /*  byte data  */
    `define BYTE_DATA_WIDTH     8
    `define BYTE_MSB            (`BYTE_DATA_WIDTH-1)
    `define BYTE_DATA_BUS       `BYTE_MSB:`LSB

    /*  word data  */
    `define WORD_DATA_WIDTH     32
    `define WORD_MSB            (`WORD_DATA_WIDTH-1)
    `define WORD_DATA_BUS       `WORD_MSB:`LSB

    /*  word address  */
    `define WORD_ADDR_WIDTH     30
    `define WORD_ADDR_MSB       (`WORD_ADDR_WIDTH-1)
    `define WORD_ADDR_BUS       `WORD_ADDR_MSB:`LSB

    /*  address offset  */
    `define BYTE_OFFSET_WIDTH   2
    `define BYTE_OFFSET_MSB     (`BYTE_OFFSET_WIDTH-1)
    `define BYTE_OFFSET_BUS     `BYTE_OFFSET_MSB:`LSB

    /*  address location  */
    `define WORD_ADDR_LOC       `WORD_ADDR_MSB:`BYTE_OFFSET_WIDTH
    `define BYTE_OFFSET_LOC     `BYTE_OFFSET_MSB:`LSB
    `define BYTE_OFFSET_WORD    2'b00

`endif

CPU/cpu_def.v
`ifndef __CPU_DEF__
    `define __CPU_DEF__

        `include "./Global/global_std_def.v"

        /*  Register  */
        `define REG_NUM         32
        `define REG_ADDR_WIDTH  5
        `define REG_ADDR_BUS    (`REG_ADDR_WIDTH-1):`LSB

        /*  IRQ Channel  */
        `define CPU_IRQ_CH      8

        /*  ALU OP Bus  */
        `define ALU_OP_WIDTH    4
        `define ALU_OP_BUS      (`ALU_OP_WIDTH-1):`LSB

        /*  ALU OP  */
        `define ALU_OP_NOP      4'h0
        `define ALU_OP_AND      4'h1
        `define ALU_OP_OR       4'h2
        `define ALU_OP_XOR      4'h3
        `define ALU_OP_ADDS     4'h4
        `define ALU_OP_ADDU     4'h5
        `define ALU_OP_SUBS     4'h6
        `define ALU_OP_SUBU     4'h7
        `define ALU_OP_SHRL     4'h8
        `define ALU_OP_SHLL     4'h9

        /*  MEM OP Bus  */
        `define MEM_OP_WIDTH    2
        `define MEM_OP_BUS      (`MEM_OP_WIDTH-1):`LSB

        /*  MEM OP  */
        `define MEM_OP_NOP      2'h0
        `define MEM_OP_LDW      2'h1
        `define MEM_OP_STW      2'h2

        /*  CTRL OP Bus  */
        `define CTRL_OP_WIDTH   2
        `define CTRL_OP_BUS     (`CTRL_OP_WIDTH-1):`LSB

        /*  CTRL OP  */
        `define CTRL_OP_NOP     2'h0
        `define CTRL_OP_WRCR    2'h1
        `define CTRL_OP_EXRT    2'h2

        /*  CPU EXE Mode Bus  */
        `define CPU_EXE_MODE_WIDTH  1
        `define CPU_EXE_MODE_BUS    (`CPU_EXE_MODE_WIDTH-1):`LSB

        /*  CPU EXE Mode  */
        `define CPU_KERNEL_MODE     1'b0
        `define CPU_USER_MODE       1'b1

        /*  CREG ADDR  */
        `define CREG_ADDR_STATUS        5'h0
        `define CREG_ADDR_RRE_STATUS    5'h1
        `define CREG_ADDR_PC            5'h2
        `define CREG_ADDR_EPC           5'h3
        `define CREG_ADDR_EXP_VECTOR    5'h4
        `define CREG_ADDR_CAUSE         5'h5
        `define CREG_ADDR_INT_MASK      5'h6
        `define CREG_ADDR_IRQ           5'h7

        `define CREG_ADDR_ROM_SIZE      5'h1d
        `define CREG_ADDR_SPM_SIZE      5'h1e
        `define CREG_ADDR_CPU_INFO      5'h1f

        /*  CREG Loc  */
        `define CREG_EXE_MODE_LOC       0
        `define CREG_INT_ENABLE_LOC     1
        `define CREG_EXP_CODE_LOC       2:0
        `define CREG_DLY_FLAG_LOC       3

        /*  BUS IF State Bus  */
        `define BUS_IF_STATE_BUS        1:`LSB

        /*  BUS IF State  */
        `define BUS_IF_STATE_IDLE       2'h0
        `define BUS_IF_STATE_REQ        2'h1
        `define BUS_IF_STATE_ACCESS     2'h2
        `define BUS_IF_STATE_STALL      2'h3

        /*  ???  */
        `define RESET_VECTOR            30'h0
        `define SH_AMOUNT_BUS           4:0
        `define SH_AMOUNT_LOC           4:0

        /*  Release  */
        `define RELEASE_YEAR            8'd41
        `define RELEASE_MONTH           8'd7
        `define RELEASE_VERSION         8'd1
        `define RELEASE_REVISION        8'd0

`endif

Bus/bus_def.v
`ifndef __BUS_DEF__
    `define __BUS_DEF__

    `include "./Global/global_std_def.v"

    /*  bus master num  */
    `define BUS_MASTER_CH           4
    `define BUS_MASTER_INDEX_WIDTH  2

    /*  bus master owner bus  */
    `define BUS_OWNER_BUS           (`BUS_MASTER_INDEX_WIDTH-1):`LSB

    /*  bus owner master  */
    `define BUS_OWNER_MASTER_0      2'h0
    `define BUS_OWNER_MASTER_1      2'h1
    `define BUS_OWNER_MASTER_2      2'h2
    `define BUS_OWNER_MASTER_3      2'h3

    /*  bus slave num  */
    `define BUS_SLAVE_CH            8
    `define BUS_SLAVE_INDEX_WIDTH   3

    /*  bus slave index bus  */
    `define BUS_SLAVE_INDEX_BUS     (`BUS_SLAVE_INDEX_WIDTH-1):`LSB
    /*  bus slave index map to address bus */
    `define BUS_SLAVE_INDEX_LOC     29:27

    /*  bus slave  */
    `define BUS_SLAVE_0     3'h0
    `define BUS_SLAVE_1     3'h1
    `define BUS_SLAVE_2     3'h2
    `define BUS_SLAVE_3     3'h3
    `define BUS_SLAVE_4     3'h4
    `define BUS_SLAVE_5     3'h5
    `define BUS_SLAVE_6     3'h6
    `define BUS_SLAVE_7     3'h7

`endif

IP/cpu_spm_dpram.v
`include "./CPU/cpu_spm_def.v"
`include "./Global/global_std_def.v"

/*  Dual Port RAM  */
module cpu_spm_dpram(
    /*  Port A  */
    input wire clka,
    input wire [`SPM_ADDR_BUS] addra,
    input wire [`WORD_DATA_BUS] dina,
    input wire wea,
    output reg [`WORD_DATA_BUS] douta,

    /*  Port B  */
    input wire clkb,
    input wire [`SPM_ADDR_BUS] addrb,
    input wire [`WORD_DATA_BUS] dinb,
    input wire web,
    output reg [`WORD_DATA_BUS] doutb
);

    reg [`WORD_DATA_BUS] ram_block [`SPM_DEPTH-1:0];

    always @(posedge clka)
    begin
        /*  read  */
        douta <= ram_block[addra];

        /*  write  */
        if(wea == `ENABLE)
        begin
            ram_block[addra] <= dina;
        end
    end

    always @(posedge clkb)
    begin
        /*  read  */
        doutb <= ram_block[addrb];

        /*  write  */
        if(web == `ENABLE)
        begin
            ram_block[addrb] <= dinb;
        end
    end

endmodule // cpu_spm_dpram

CPU/cpu_spm_def.v
`ifndef __CPU_SPM_DEF__
    `define __CPU_SPM_DEF__

    `include "./Global/global_std_def.v"

    `define SPM_SIZE        16384
    `define SPM_DEPTH       4096
    `define SPM_ADDR_WIDTH  12
    `define SPM_ADDR_BUS    (`SPM_ADDR_WIDTH-1):`LSB
    `define SPM_ADDR_LOC    11:0

`endif

CPU/cpu_bus_if.v
`include "./CPU/cpu_spm_def.v"
`include "./IP/cpu_spm_dpram.v"
`include "./Global/global_std_def.v"
`include "./Global/global_cfg_def.v"
`include "./Bus/bus_def.v"
`include "./CPU/cpu_def.v"

// book is wrong??? (p112-wire->reg)
module cpu_bus_if(
    /*  clk & reset  */
    input wire clk,
    input wire reset,

    /*  pipeline control signal  */
    input wire stall,
    input wire flush,
    output reg busy,

    /*  cpu interface  */
    input wire [`WORD_ADDR_BUS] addr,
    input wire as_n,
    input wire rw,
    input wire [`WORD_DATA_BUS] wr_data,
    output reg [`WORD_DATA_BUS] rd_data,

    /*  spm interface  */
    output wire [`WORD_ADDR_BUS] spm_addr,
    output reg spm_as_n,
    output wire spm_rw,
    input wire [`WORD_DATA_BUS] spm_rd_data,
    output wire [`WORD_DATA_BUS] spm_wr_data,

    /*  bus interface / control  */
    input wire bus_rdy_n,
    input wire bus_grnt_n,
    output reg bus_req_n,

    /*  bus interface / data  */
    output reg [`WORD_ADDR_BUS] bus_addr,
    output reg bus_as_n,
    output reg bus_rw,
    input wire [`WORD_DATA_BUS] bus_rd_data,
    output reg [`WORD_DATA_BUS] bus_wr_data
);

    reg [1:0] state;
    reg [31:0] rd_buf;  /*  read buffer  */
    wire [2:0] s_index; /*  bus slave index  */

    /*  SPM Control  */
    /*  Bus Slave Index  */
    assign s_index = addr[`BUS_SLAVE_INDEX_LOC];
    /*  output wire  */
    assign spm_addr = addr;
    assign spm_rw = rw;
    assign spm_wr_data = wr_data;
    
    /*  SPM Access Control  */
    always @(*)
    begin
        /*  default  */
        rd_data = `WORD_DATA_WIDTH'h0;
        spm_as_n = `DISABLE_;
        busy = `DISABLE;
        /*  bus status  */
        case(state)
            `BUS_IF_STATE_IDLE : /*  IDLE  */
            begin
                /*  SPM Access  */
                if((flush == `DISABLE) && (as_n == `ENABLE_))
                begin
                    /*  Access SPM  */
                    if(s_index == `BUS_SLAVE_1)
                    begin
                        if(stall == `DISABLE)   // Detect for stall
                        begin
                            spm_as_n = `ENABLE_;
                            if(rw == `READ) // Read Access
                            begin
                                rd_data = spm_rd_data;
                            end
                        end
                    end
                    else
                    begin
                        /*  Access Bus  */
                        busy = `ENABLE;
                    end
                end
            end
            `BUS_IF_STATE_REQ : /*  Request Bus  */
            begin
                busy = `ENABLE;
            end
            `BUS_IF_STATE_ACCESS :
            begin
                /*  Wait for Ready  */
                if(bus_rdy_n == `ENABLE_)   // Wait for Ready
                begin
                    if(rw == `READ) // Read Access
                    begin
                        rd_data = bus_rd_data;
                    end
                end
                else
                begin
                    // no Ready Signal
                    busy = `ENABLE;
                end
            end
            `BUS_IF_STATE_STALL : // Stall
            begin
                if(rw == `READ) // Read Accesss
                begin
                    rd_data = rd_buf;
                end
            end
        endcase
    end

    /*  Bus Control  */
    always @(posedge clk or `RESET_EDGE reset)
    begin
        if(reset == `RESET_ENABLE)
        begin
            /*  reset  */
            state       <= #1 `BUS_IF_STATE_IDLE;
            bus_req_n   <= #1 `DISABLE_;
            bus_addr    <= #1 `WORD_ADDR_WIDTH'h0;
            bus_as_n    <= #1 `DISABLE_;
            bus_rw      <= #1 `READ;
            bus_wr_data <= #1 `WORD_DATA_WIDTH'h0;
            rd_buf      <= #1 `WORD_DATA_WIDTH'h0;
        end
        else
        begin
            /*  bus state  */
            case(state)
                `BUS_IF_STATE_IDLE : // idle
                begin
                    /*  SPM Access  */
                    if((flush ==  `DISABLE) && (as_n ==`ENABLE_))
                    begin
                        /*  Choose Access Object  */
                        if(s_index != `BUS_SLAVE_1)
                        begin
                            /*  Access Bus  */
                            state       <= #1 `BUS_IF_STATE_REQ;
                            bus_req_n   <= #1 `ENABLE_;
                            bus_addr    <= #1 addr;
                            bus_rw      <= #1 rw;
                            bus_wr_data <= #1 wr_data;
                        end
                    end 
                end
                `BUS_IF_STATE_REQ : // Request Bus
                begin
                    /*  Wait for Bus Granted  */
                    if(bus_grnt_n == `ENABLE_)
                    begin
                        state       <= #1 `BUS_IF_STATE_ACCESS;
                        bus_as_n    <= #1 `ENABLE_;
                    end
                end
                `BUS_IF_STATE_ACCESS : // Access Bus
                begin
                    bus_as_n    <= #1 `DISABLE_;
                    /*  Wait for Ready  */
                    if(bus_rdy_n == `ENABLE_)
                    begin
                        bus_req_n   <= #1 `DISABLE_;
                        bus_addr    <= #1 `WORD_ADDR_WIDTH'h0;
                        bus_rw      <= #1 `READ;
                        bus_wr_data <= #1 `WORD_DATA_WIDTH'h0;
                        /*  Save Read Data  */
                        if(bus_rw == `READ)
                        begin
                            rd_buf  <= #1 bus_rd_data;
                        end
                        /*  Detect Stall  */
                        if(stall == `ENABLE)
                        begin
                            /*  stall  */
                            state   <= #1 `BUS_IF_STATE_STALL;
                        end
                        else
                        begin
                            /*  not stall  */
                            state   <= #1 `BUS_IF_STATE_IDLE;
                        end
                    end
                end
                `BUS_IF_STATE_STALL : // Stall
                begin
                    /*  Detect Stall  */
                    if(stall == `DISABLE)
                    begin
                        state   <= #1 `BUS_IF_STATE_IDLE;
                    end
                end
            endcase
        end
    end
endmodule // bus_if

CPU/testbench/cpu_bus_if_tb.v
`timescale 1ns/100ps

`include "./CPU/cpu_bus_if.v"
`include "./Global/global_std_def.v"
`include "./Global/global_cfg_def.v"

module cpu_bus_if_tb;

    /*  clk & reset  */
    reg clk=0;
    reg reset=1;

    /*  pipeline control signal  */
    reg stall=0;
    reg flush=0;
    wire busy;

    /*  cpu interface  */
    reg [`WORD_ADDR_BUS] addr;
    reg as_n=`DISABLE_;
    reg rw=`READ;
    reg [`WORD_DATA_BUS] wr_data=`WORD_DATA_WIDTH'h123456;
    wire [`WORD_DATA_BUS] rd_data;

    /*  spm interface  */
    wire [`WORD_ADDR_BUS] spm_addr;
    wire spm_as_n;
    wire spm_rw;
    reg [`WORD_DATA_BUS] spm_rd_data=`WORD_DATA_WIDTH'h234567;
    wire [`WORD_DATA_BUS] spm_wr_data;

    /*  bus interface / control  */
    reg bus_rdy_n=`DISABLE_;
    reg bus_grnt_n=`DISABLE_;
    wire bus_req_n;

    /*  bus interface / data  */
    wire [`WORD_ADDR_BUS] bus_addr;
    wire bus_as_n;
    wire bus_rw;
    reg [`WORD_DATA_BUS] bus_rd_data=`WORD_DATA_WIDTH'h345678;
    wire [`WORD_DATA_BUS] bus_wr_data;


    cpu_bus_if cpu_bus_if_01(
        /*  clk & reset  */
        clk,
        reset,
        
        /*  pipeline control signal  */
        stall,
        flush,
        busy,

        /*  cpu interface  */
        addr,
        as_n,
        rw,
        wr_data,
        rd_data,

        /*  spm interface  */
        spm_addr,
        spm_as_n,
        spm_rw,
        spm_rd_data,
        spm_wr_data,

        /*  bus interface / control  */
        bus_rdy_n,
        bus_grnt_n,
        bus_req_n,

        /*  bus interface / data  */
        bus_addr,
        bus_as_n,
        bus_rw,
        bus_rd_data,
        bus_wr_data
    );

    /*  clock  */
    always
        #10 clk = ~clk;


    /*  testbench  */
    initial
    begin
        $dumpfile("cpu_bus_if.vcd");
        $dumpvars(0,cpu_bus_if_tb);
        
        #40 reset=0;
        #40 reset=1;

        #40 addr = {3'b001,27'h0};
        #40 as_n = `ENABLE_;
        flush = `DISABLE;
        #40 addr = {3'b010,27'h1234};

        #40 bus_grnt_n = `ENABLE_;
        #40 bus_rdy_n = `ENABLE_;
        stall = `ENABLE;

        #40 stall = `DISABLE;

        #100 $finish;
    end



endmodule // cpu_bus_if_tb

CPU/testbench/cpu_bus_if.vcd
$date
	Wed Nov 20 12:02:53 2019
$end
$version
	Icarus Verilog
$end
$timescale
	100ps
$end
$scope module cpu_bus_if_tb $end
$var wire 32 ! spm_wr_data [31:0] $end
$var wire 1 " spm_rw $end
$var wire 1 # spm_as_n $end
$var wire 30 $ spm_addr [29:0] $end
$var wire 32 % rd_data [31:0] $end
$var wire 1 & busy $end
$var wire 32 ' bus_wr_data [31:0] $end
$var wire 1 ( bus_rw $end
$var wire 1 ) bus_req_n $end
$var wire 1 * bus_as_n $end
$var wire 30 + bus_addr [29:0] $end
$var reg 30 , addr [29:0] $end
$var reg 1 - as_n $end
$var reg 1 . bus_grnt_n $end
$var reg 32 / bus_rd_data [31:0] $end
$var reg 1 0 bus_rdy_n $end
$var reg 1 1 clk $end
$var reg 1 2 flush $end
$var reg 1 3 reset $end
$var reg 1 4 rw $end
$var reg 32 5 spm_rd_data [31:0] $end
$var reg 1 6 stall $end
$var reg 32 7 wr_data [31:0] $end
$scope module cpu_bus_if_01 $end
$var wire 30 8 addr [29:0] $end
$var wire 1 - as_n $end
$var wire 1 . bus_grnt_n $end
$var wire 32 9 bus_rd_data [31:0] $end
$var wire 1 0 bus_rdy_n $end
$var wire 1 1 clk $end
$var wire 1 2 flush $end
$var wire 1 3 reset $end
$var wire 1 4 rw $end
$var wire 30 : spm_addr [29:0] $end
$var wire 32 ; spm_rd_data [31:0] $end
$var wire 1 " spm_rw $end
$var wire 32 < spm_wr_data [31:0] $end
$var wire 1 6 stall $end
$var wire 32 = wr_data [31:0] $end
$var wire 3 > s_index [2:0] $end
$var reg 30 ? bus_addr [29:0] $end
$var reg 1 * bus_as_n $end
$var reg 1 ) bus_req_n $end
$var reg 1 ( bus_rw $end
$var reg 32 @ bus_wr_data [31:0] $end
$var reg 1 & busy $end
$var reg 32 A rd_buf [31:0] $end
$var reg 32 B rd_data [31:0] $end
$var reg 1 # spm_as_n $end
$var reg 2 C state [1:0] $end
$upscope $end
$upscope $end
$enddefinitions $end
#0
$dumpvars
bx C
b0 B
bx A
bx @
bx ?
bx >
b100100011010001010110 =
b100100011010001010110 <
b1000110100010101100111 ;
bx :
b1101000101011001111000 9
bx 8
b100100011010001010110 7
06
b1000110100010101100111 5
14
13
02
01
10
b1101000101011001111000 /
1.
1-
bx ,
bx +
x*
x)
x(
bx '
0&
b0 %
bx $
1#
1"
b100100011010001010110 !
$end
#100
11
#200
01
#300
11
#400
01
03
#410
b0 A
b0 '
b0 @
1(
1*
b0 +
b0 ?
1)
b0 C
#500
11
#600
01
#700
11
#800
01
13
#900
11
#1000
01
#1100
11
#1200
b1 >
01
b1000000000000000000000000000 $
b1000000000000000000000000000 :
b1000000000000000000000000000 ,
b1000000000000000000000000000 8
#1300
11
#1400
01
#1500
11
#1600
b1000110100010101100111 %
b1000110100010101100111 B
0#
01
0-
#1700
11
#1800
01
#1900
11
#2000
1&
1#
b0 %
b0 B
b10 >
01
b10000000000000001001000110100 $
b10000000000000001001000110100 :
b10000000000000001001000110100 ,
b10000000000000001001000110100 8
#2100
11
#2110
1&
b100100011010001010110 '
b100100011010001010110 @
b10000000000000001001000110100 +
b10000000000000001001000110100 ?
0)
b1 C
#2200
01
#2300
11
#2400
01
0.
#2500
11
#2510
1&
0*
b10 C
#2600
01
#2700
11
#2710
1*
#2800
b1101000101011001111000 %
b1101000101011001111000 B
0&
01
16
00
#2900
11
#2910
b1101000101011001111000 %
b1101000101011001111000 B
b11 C
b1101000101011001111000 A
b0 '
b0 @
b0 +
b0 ?
1)
#3000
01
#3100
11
#3200
b1101000101011001111000 %
b1101000101011001111000 B
01
06
#3300
11
#3310
1&
b0 %
b0 B
b0 C
#3400
01
#3500
11
#3510
1&
b100100011010001010110 '
b100100011010001010110 @
b10000000000000001001000110100 +
b10000000000000001001000110100 ?
0)
b1 C
#3600
01
#3700
11
#3710
b1101000101011001111000 %
b1101000101011001111000 B
0&
0*
b10 C
#3800
01
#3900
11
#3910
1&
b0 %
b0 B
b0 C
b0 '
b0 @
b0 +
b0 ?
1)
1*
#4000
01
#4100
11
#4110
1&
b100100011010001010110 '
b100100011010001010110 @
b10000000000000001001000110100 +
b10000000000000001001000110100 ?
0)
b1 C
