Global/global_std_def.v
`ifndef __GLOBAL_STD_DEF__
    `define __GLOBAL_STD_DEF__

    /*  singal level  */
    `define HIGH        1'b1
    `define LOW         1'b0

    /*  enable & disable  */
    `define DISABLE     1'b0
    `define ENABLE      1'b1
    `define DISABLE_    1'b1
    `define ENABLE_     1'b0

    /*  read & write  */
    `define READ        1'b1
    `define WRITE       1'b0

    /*  Least Significant Bit  */
    `define LSB         0

    /*  byte data  */
    `define BYTE_DATA_WIDTH     8
    `define BYTE_MSB            (`BYTE_DATA_WIDTH-1)
    `define BYTE_DATA_BUS       `BYTE_MSB:`LSB

    /*  word data  */
    `define WORD_DATA_WIDTH     32
    `define WORD_MSB            (`WORD_DATA_WIDTH-1)
    `define WORD_DATA_BUS       `WORD_MSB:`LSB

    /*  word address  */
    `define WORD_ADDR_WIDTH     30
    `define WORD_ADDR_MSB       (`WORD_ADDR_WIDTH-1)
    `define WORD_ADDR_BUS       `WORD_ADDR_MSB:`LSB

    /*  address offset  */
    `define BYTE_OFFSET_WIDTH   2
    `define BYTE_OFFSET_MSB     (`BYTE_OFFSET_WIDTH-1)
    `define BYTE_OFFSET_BUS     `BYTE_OFFSET_MSB:`LSB

    /*  address location  */
    `define WORD_ADDR_LOC       `WORD_ADDR_MSB:`BYTE_OFFSET_WIDTH
    `define BYTE_OFFSET_LOC     `BYTE_OFFSET_MSB:`LSB
    `define BYTE_OFFSET_WORD    2'b00

`endif

CPU/cpu_spm_def.v
`ifndef __CPU_SPM_DEF__
    `define __CPU_SPM_DEF__

    `include "./Global/global_std_def.v"

    `define SPM_SIZE        16384
    `define SPM_DEPTH       4096
    `define SPM_ADDR_WIDTH  12
    `define SPM_ADDR_BUS    (`SPM_ADDR_WIDTH-1):`LSB
    `define SPM_ADDR_LOC    11:0

`endif

Global/global_cfg_def.v
`ifndef __GLOBAL_CFG_DEF__
    `define __GLOBAL_CFG_DEF__

    /*  choose RESET polarity  */
    // `define POSITIVE_RESET
    `define NEGATIVE_RESET

    /*  choose MEMORY polarity  */
    `define POSITIVE_MEMORY
    // `define NEGATIVE_MRMORY

    /*  Enable I/O Modules  */
    // `define IMPLEMENT_TIMER
    // `define IMPLEMENT_UART
    // `define IMPLEMENT_GPIO

    /*  generate RESET_ENABLE & RESET_DISABLE & RESET_EDGE */
    // book is wrong???
    // `ifdef POSITIVE_RESET
    //     `define RESET_EDGE      posedge
    //     `define RESET_ENABLE    1'b0
    //     `define RESET_DISABLE   1'b1
    // `elif NEGATIVE_RESET
        `define RESET_EDGE      negedge
        `define RESET_ENABLE    1'b1
        `define RESET_DISABLE   1'b0
    // `endif
    

    /*  generate MEM_ENABLE & MEM_DISABLE  */
    // `ifdef POSITIVE_MEMORY
        `define MEM_ENABLE    1'b1
        `define MEM_DISABLE   1'b0
    // `elif NEGATIVE_MRMORY
    //     `define MEM_ENABLE    1'b0
    //     `define MEM_DISABLE   1'b1
    // `endif

`endif

IP/cpu_spm_dpram.v
`include "./CPU/cpu_spm_def.v"
`include "./Global/global_std_def.v"

/*  Dual Port RAM  */
module cpu_spm_dpram(
    /*  Port A  */
    input wire clka,
    input wire [`SPM_ADDR_BUS] addra,
    input wire [`WORD_DATA_BUS] dina,
    input wire wea,
    output reg [`WORD_DATA_BUS] douta,

    /*  Port B  */
    input wire clkb,
    input wire [`SPM_ADDR_BUS] addrb,
    input wire [`WORD_DATA_BUS] dinb,
    input wire web,
    output reg [`WORD_DATA_BUS] doutb
);

    reg [`WORD_DATA_BUS] ram_block [`SPM_DEPTH-1:0];

    always @(posedge clka)
    begin
        /*  read  */
        douta <= ram_block[addra];

        /*  write  */
        if(wea == `ENABLE)
        begin
            ram_block[addra] <= dina;
        end
    end

    always @(posedge clkb)
    begin
        /*  read  */
        doutb <= ram_block[addrb];

        /*  write  */
        if(web == `ENABLE)
        begin
            ram_block[addrb] <= dinb;
        end
    end

endmodule // cpu_spm_dpram

CPU/cpu_spm.v
`include "./CPU/cpu_spm_def.v"
`include "./IP/cpu_spm_dpram.v"
`include "./Global/global_cfg_def.v"
`include "./Global/global_std_def.v"

/*  Scratch Pad Memory  */
module cpu_spm(
    /*  clock  */
    input wire clk,

    /*  Port A / IF  */
    input wire [`SPM_ADDR_BUS] if_spm_addr,
    input wire if_spm_as_n,
    input wire if_spm_rw,
    input wire [`WORD_DATA_BUS] if_spm_wr_data,
    output wire [`WORD_DATA_BUS] if_spm_rd_data,

    /*  Port B / MEM  */
    input wire [`SPM_ADDR_BUS] mem_spm_addr,
    input wire mem_spm_as_n,
    input wire mem_spm_rw,
    input wire [`WORD_DATA_BUS] mem_spm_wr_data,
    output wire [`WORD_DATA_BUS] mem_spm_rd_data
);
    /*  Write Enable  */
    reg wea,web;

    /*  Generate Write Enable Signal */
    always @(*)
    begin
        /*  Port A  */
        if ((if_spm_as_n == `ENABLE_) && (if_spm_rw == `WRITE))
        begin
            wea = `MEM_ENABLE;  // Memory Write Enable
        end
        else
        begin
            wea = `MEM_DISABLE;  // Memory Write Disable
        end

        /*  Port B  */
        if ((mem_spm_as_n == `ENABLE_) && (mem_spm_rw == `WRITE))
        begin
            web = `MEM_ENABLE;  // Memory Write Enable
        end
        else
        begin
            web = `MEM_DISABLE;  // Memory Write Disable
        end
    end

    /*  Dual Port RAM  */
    cpu_spm_dpram dpram_01(
        /*  Port A / IF  */
        .clka   (clk),
        .addra  (if_spm_addr),
        .dina   (if_spm_wr_data),
        .wea    (wea),
        .douta  (if_spm_rd_data),

        /*  Port B / MEM  */
        .clkb   (clk),
        .addrb  (mem_spm_addr),
        .dinb   (mem_spm_wr_data),
        .web    (web),
        .doutb  (mem_spm_rd_data)
    );

endmodule // cpu_spm

CPU/testbench/cpu_spm_tb.v
`timescale 1ns/100ps
`include "./CPU/cpu_spm_def.v"
`include "./CPU/cpu_spm.v"
`include "./Global/global_std_def.v"

module cpu_spm_tb;

    /*  clock  */
    reg clk = `LOW;

    /*  Port A / IF  */
    reg [`SPM_ADDR_BUS] if_spm_addr;
    reg if_spm_as_n = `DISABLE_;
    reg if_spm_rw = `READ;
    reg [`WORD_DATA_BUS] if_spm_wr_data;
    wire [`WORD_DATA_BUS] if_spm_rd_data;

    /*  Port B / MEM  */
    reg [`SPM_ADDR_BUS] mem_spm_addr;
    reg mem_spm_as_n = `DISABLE_;
    reg mem_spm_rw = `READ;
    reg [`WORD_DATA_BUS] mem_spm_wr_data;
    wire [`WORD_DATA_BUS] mem_spm_rd_data;

    cpu_spm cpu_spm_01(
        /*  clock  */
        clk,

        /*  Port A / IF  */
        if_spm_addr,
        if_spm_as_n,
        if_spm_rw,
        if_spm_wr_data,
        if_spm_rd_data,

        /*  Port B / MEM  */
        mem_spm_addr,
        mem_spm_as_n,
        mem_spm_rw,
        mem_spm_wr_data,
        mem_spm_rd_data
    );

    /*  clock  */
    always
        #10 clk = ~clk;

    integer i;
    
    /*  testbench  */
    initial
    begin
        $dumpfile("cpu_spm.vcd");
        $dumpvars(0,cpu_spm_tb);
        
        /*  set rom data to zero  */
        for(i=0;i<`SPM_DEPTH;i=i+1)
        begin
            cpu_spm_01.dpram_01.ram_block[i] = 0;
        end

        // mem port read addr 0
        #40 mem_spm_addr = 0;
        mem_spm_as_n = `ENABLE_;
        mem_spm_rw = `READ;
        // if port write addr 0
        #50 if_spm_addr = 0;
        if_spm_wr_data = `WORD_DATA_WIDTH'h1234;
        #50 if_spm_rw = `WRITE;
        #50 if_spm_as_n = `ENABLE_;
        // if port read addr 1
        #50 if_spm_as_n = `DISABLE_;
        #50 if_spm_rw = `READ;
        if_spm_addr = 1;
        // mem port write addr 1
        #50 mem_spm_addr = 1;
        mem_spm_wr_data = `WORD_DATA_WIDTH'habcd;
        #50 mem_spm_rw = `WRITE;

        #100 $finish;
    end

endmodule // cpu_spm_tb

CPU/testbench/cpu_spm.vcd
$date
	Thu Nov 14 16:04:37 2019
$end
$version
	Icarus Verilog
$end
$timescale
	100ps
$end
$scope module cpu_spm_tb $end
$var wire 32 ! mem_spm_rd_data [31:0] $end
$var wire 32 " if_spm_rd_data [31:0] $end
$var reg 1 # clk $end
$var reg 12 $ if_spm_addr [11:0] $end
$var reg 1 % if_spm_as_n $end
$var reg 1 & if_spm_rw $end
$var reg 32 ' if_spm_wr_data [31:0] $end
$var reg 12 ( mem_spm_addr [11:0] $end
$var reg 1 ) mem_spm_as_n $end
$var reg 1 * mem_spm_rw $end
$var reg 32 + mem_spm_wr_data [31:0] $end
$var integer 32 , i [31:0] $end
$scope module cpu_spm_01 $end
$var wire 1 # clk $end
$var wire 12 - if_spm_addr [11:0] $end
$var wire 1 % if_spm_as_n $end
$var wire 1 & if_spm_rw $end
$var wire 32 . if_spm_wr_data [31:0] $end
$var wire 12 / mem_spm_addr [11:0] $end
$var wire 1 ) mem_spm_as_n $end
$var wire 1 * mem_spm_rw $end
$var wire 32 0 mem_spm_wr_data [31:0] $end
$var wire 32 1 mem_spm_rd_data [31:0] $end
$var wire 32 2 if_spm_rd_data [31:0] $end
$var reg 1 3 wea $end
$var reg 1 4 web $end
$scope module dpram_01 $end
$var wire 12 5 addra [11:0] $end
$var wire 12 6 addrb [11:0] $end
$var wire 1 # clka $end
$var wire 1 # clkb $end
$var wire 32 7 dina [31:0] $end
$var wire 32 8 dinb [31:0] $end
$var wire 1 3 wea $end
$var wire 1 4 web $end
$var reg 32 9 douta [31:0] $end
$var reg 32 : doutb [31:0] $end
$upscope $end
$upscope $end
$upscope $end
$enddefinitions $end
#0
$dumpvars
bx :
bx 9
bx 8
bx 7
bx 6
bx 5
04
03
bx 2
bx 1
bx 0
bx /
bx .
bx -
b1000000000000 ,
bx +
1*
1)
bx (
bx '
1&
1%
bx $
0#
bx "
bx !
$end
#100
1#
#200
0#
#300
1#
#400
0#
0)
b0 (
b0 /
b0 6
#500
b0 !
b0 1
b0 :
1#
#600
0#
#700
1#
#800
0#
#900
b0 "
b0 2
b0 9
1#
b1001000110100 '
b1001000110100 .
b1001000110100 7
b0 $
b0 -
b0 5
#1000
0#
#1100
1#
#1200
0#
#1300
1#
#1400
0#
0&
#1500
1#
#1600
0#
#1700
1#
#1800
0#
#1900
13
1#
0%
#2000
0#
#2100
b1001000110100 "
b1001000110100 2
b1001000110100 9
b1001000110100 !
b1001000110100 1
b1001000110100 :
1#
#2200
0#
#2300
1#
#2400
03
0#
1%
#2500
1#
#2600
0#
#2700
1#
#2800
0#
#2900
b0 "
b0 2
b0 9
1#
b1 $
b1 -
b1 5
1&
#3000
0#
#3100
1#
#3200
0#
#3300
1#
#3400
0#
b1010101111001101 +
b1010101111001101 0
b1010101111001101 8
b1 (
b1 /
b1 6
#3500
b0 !
b0 1
b0 :
1#
#3600
0#
#3700
1#
#3800
0#
#3900
14
1#
0*
#4000
0#
#4100
b1010101111001101 "
b1010101111001101 2
b1010101111001101 9
b1010101111001101 !
b1010101111001101 1
b1010101111001101 :
1#
