Global/global_std_def.v
`ifndef __GLOBAL_STD_DEF__
    `define __GLOBAL_STD_DEF__

    /*  singal level  */
    `define HIGH        1'b1
    `define LOW         1'b0

    /*  enable & disable  */
    `define DISABLE     1'b0
    `define ENABLE      1'b1
    `define DISABLE_    1'b1
    `define ENABLE_     1'b0

    /*  read & write  */
    `define READ        1'b1
    `define WRITE       1'b0

    /*  Least Significant Bit  */
    `define LSB         0

    /*  byte data  */
    `define BYTE_DATA_WIDTH     8
    `define BYTE_MSB            (`BYTE_DATA_WIDTH-1)
    `define BYTE_DATA_BUS       `BYTE_MSB:`LSB

    /*  word data  */
    `define WORD_DATA_WIDTH     32
    `define WORD_MSB            (`WORD_DATA_WIDTH-1)
    `define WORD_DATA_BUS       `WORD_MSB:`LSB

    /*  word address  */
    `define WORD_ADDR_WIDTH     30
    `define WORD_ADDR_MSB       (`WORD_ADDR_WIDTH-1)
    `define WORD_ADDR_BUS       `WORD_ADDR_MSB:`LSB

    /*  address offset  */
    `define BYTE_OFFSET_WIDTH   2
    `define BYTE_OFFSET_MSB     (`BYTE_OFFSET_WIDTH-1)
    `define BYTE_OFFSET_BUS     `BYTE_OFFSET_MSB:`LSB

    /*  address location  */
    `define WORD_ADDR_LOC       `WORD_ADDR_MSB:`BYTE_OFFSET_WIDTH
    `define BYTE_OFFSET_LOC     `BYTE_OFFSET_MSB:`LSB
    `define BYTE_OFFSET_WORD    2'b00

`endif

Global/global_cfg_def.v
`ifndef __GLOBAL_CFG_DEF__
    `define __GLOBAL_CFG_DEF__

    /*  choose RESET polarity  */
    // `define POSITIVE_RESET
    `define NEGATIVE_RESET

    /*  choose MEMORY polarity  */
    `define POSITIVE_MEMORY
    // `define NEGATIVE_MRMORY

    /*  Enable I/O Modules  */
    // `define IMPLEMENT_TIMER
    // `define IMPLEMENT_UART
    // `define IMPLEMENT_GPIO

    /*  generate RESET_ENABLE & RESET_DISABLE & RESET_EDGE */
    // book is wrong???
    // `ifdef POSITIVE_RESET
    //     `define RESET_EDGE      posedge
    //     `define RESET_ENABLE    1'b0
    //     `define RESET_DISABLE   1'b1
    // `elif NEGATIVE_RESET
        `define RESET_EDGE      negedge
        `define RESET_ENABLE    1'b1
        `define RESET_DISABLE   1'b0
    // `endif
    

    /*  generate MEM_ENABLE & MEM_DISABLE  */
    // `ifdef POSITIVE_MEMORY
        `define MEM_ENABLE    1'b1
        `define MEM_DISABLE   1'b0
    // `elif NEGATIVE_MRMORY
    //     `define MEM_ENABLE    1'b0
    //     `define MEM_DISABLE   1'b1
    // `endif

`endif

ROM/rom_def.v
`ifndef __ROM_DEF__
    `define __ROM_DEF__

    `include "./Global/global_std_def.v"

    `define ROM_SIZE        8192
    `define ROM_DEPTH       2048
    `define ROM_ADDR_WIDTH  11
    `define ROM_ADDR_BUS    (`ROM_ADDR_WIDTH-1):0
    `define ROM_ADDR_LOC    (`ROM_ADDR_WIDTH-1):0

`endif

ROM/rom.v
`timescale 1ns/100ps
`include "./ROM/rom_def.v"

module rom(
    input wire clk,
    input wire [`ROM_ADDR_BUS] addr,
    output reg [`WORD_DATA_BUS] dout
);

    reg [`WORD_DATA_BUS] rom_block [`ROM_SIZE-1:0];

    always @(posedge clk)
    begin
        dout <= rom_block[addr];
    end

    integer i;
    initial
    begin
        $readmemh("./rom_tb.dat",rom_block);
        for(i=0;i<10;i++)
        begin
            $display("addr = 0x%h,\tdata = 0x%h;\n",i,rom_block[i]);
        end
    end


endmodule // rom

ROM/rom_top.v
`include "./ROM/rom_def.v"
`include "./ROM/rom.v"
`include "./Global/global_cfg_def.v"

module rom_top(
    /*  clock & reset  */
    input wire clk,
    input wire reset,

    /*  bus  */
    input wire cs_n,
    input wire as_n,
    input wire [`ROM_ADDR_BUS] addr,
    output wire [`WORD_DATA_BUS] rd_data,
    output reg rdy_n
);

rom rom_01(
    .clk    (clk),
    .addr   (addr),
    .dout   (rd_data)
);

always @(posedge clk or `RESET_EDGE reset) begin
    if(reset == `RESET_DISABLE)     // book is wrong???
    begin
        rdy_n <= #1 `DISABLE_;
    end
    else
    begin
        if((cs_n == `ENABLE_) && (as_n == `ENABLE_ ))
        begin
            rdy_n <= #1 `ENABLE_;
        end
        else
        begin
            rdy_n <= #1 `DISABLE_;
        end
    end
end


endmodule // rom_top

ROM/testbench/rom_top_tb.v
`timescale 1ns/100ps

`include "./ROM/rom_top.v"
`include "./Global/global_std_def.v"

module rom_top_tb;

    /*  clock & reset  */
    reg clk = `LOW;
    reg reset = `RESET_DISABLE;

    /*  bus  */
    reg cs_n = `DISABLE_;
    reg as_n = `DISABLE_;
    reg [`ROM_ADDR_BUS] addr=0;
    wire [`WORD_DATA_BUS] rd_data;
    wire rdy_n;

    rom_top rom_top_01(
        /*  clock & reset  */
        clk,
        reset,

        /*  bus  */
        cs_n,
        as_n,
        addr,
        rd_data,
        rdy_n
    );


    /*  clock  */
    always
        #10 clk = ~clk;

    /*  testbench  */
    initial
    begin
        $dumpfile("rom_top.vcd");
        $dumpvars(0,rom_top_tb);
        
        #50 reset = `RESET_ENABLE;
        cs_n  = `ENABLE_;
        as_n = `ENABLE_;
        
        while(addr<10)
            #50 addr=addr+1;

        #100 $finish;
    end

endmodule // rom_top_tb

ROM/testbench/rom_top.vcd
$date
	Wed Nov 13 14:43:52 2019
$end
$version
	Icarus Verilog
$end
$timescale
	100ps
$end
$scope module rom_top_tb $end
$var wire 1 ! rdy_n $end
$var wire 32 " rd_data [31:0] $end
$var reg 11 # addr [10:0] $end
$var reg 1 $ as_n $end
$var reg 1 % clk $end
$var reg 1 & cs_n $end
$var reg 1 ' reset $end
$scope module rom_top_01 $end
$var wire 11 ( addr [10:0] $end
$var wire 1 $ as_n $end
$var wire 1 % clk $end
$var wire 1 & cs_n $end
$var wire 1 ' reset $end
$var wire 32 ) rd_data [31:0] $end
$var reg 1 ! rdy_n $end
$scope module rom_01 $end
$var wire 11 * addr [10:0] $end
$var wire 1 % clk $end
$var reg 32 + dout [31:0] $end
$var integer 32 , i [31:0] $end
$upscope $end
$upscope $end
$upscope $end
$enddefinitions $end
#0
$dumpvars
b1010 ,
bx +
b0 *
bx )
b0 (
1'
1&
0%
1$
b0 #
bx "
x!
$end
#100
b1001000110100010101100111 "
b1001000110100010101100111 )
b1001000110100010101100111 +
1%
#110
1!
#200
0%
#300
1%
#400
0%
#500
1%
0$
0&
0'
#510
0!
#600
0%
#700
1%
#800
0%
#900
1%
#1000
0%
b1 #
b1 (
b1 *
#1100
b10010001101000101011001111000 "
b10010001101000101011001111000 )
b10010001101000101011001111000 +
1%
#1200
0%
#1300
1%
#1400
0%
#1500
b100011010001010110011110001001 "
b100011010001010110011110001001 )
b100011010001010110011110001001 +
1%
b10 #
b10 (
b10 *
#1600
0%
#1700
1%
#1800
0%
#1900
1%
#2000
0%
b11 #
b11 (
b11 *
#2100
b110100010101100111100010011010 "
b110100010101100111100010011010 )
b110100010101100111100010011010 +
1%
#2200
0%
#2300
1%
#2400
0%
#2500
b1000101011001111000100110101011 "
b1000101011001111000100110101011 )
b1000101011001111000100110101011 +
1%
b100 #
b100 (
b100 *
#2600
0%
#2700
1%
#2800
0%
#2900
1%
#3000
0%
b101 #
b101 (
b101 *
#3100
b1010110011110001001101010111100 "
b1010110011110001001101010111100 )
b1010110011110001001101010111100 +
1%
#3200
0%
#3300
1%
#3400
0%
#3500
b1100111100010011010101111001101 "
b1100111100010011010101111001101 )
b1100111100010011010101111001101 +
1%
b110 #
b110 (
b110 *
#3600
0%
#3700
1%
#3800
0%
#3900
1%
#4000
0%
b111 #
b111 (
b111 *
#4100
b1111000100110101011110011011110 "
b1111000100110101011110011011110 )
b1111000100110101011110011011110 +
1%
#4200
0%
#4300
1%
#4400
0%
#4500
b10001001101010111100110111101111 "
b10001001101010111100110111101111 )
b10001001101010111100110111101111 +
1%
b1000 #
b1000 (
b1000 *
#4600
0%
#4700
1%
#4800
0%
#4900
1%
#5000
0%
b1001 #
b1001 (
b1001 *
#5100
b10011010101111001101111011110000 "
b10011010101111001101111011110000 )
b10011010101111001101111011110000 +
1%
#5200
0%
#5300
1%
#5400
0%
#5500
bx "
bx )
bx +
1%
b1010 #
b1010 (
b1010 *
