Global/global_std_def.v
`ifndef __GLOBAL_STD_DEF__
    `define __GLOBAL_STD_DEF__

    /*  singal level  */
    `define HIGH        1'b1
    `define LOW         1'b0

    /*  enable & disable  */
    `define DISABLE     1'b0
    `define ENABLE      1'b1
    `define DISABLE_    1'b1
    `define ENABLE_     1'b0

    /*  read & write  */
    `define READ        1'b1
    `define WRITE       1'b0

    /*  Least Significant Bit  */
    `define LSB         0

    /*  byte data  */
    `define BYTE_DATA_WIDTH     8
    `define BYTE_MSB            (`BYTE_DATA_WIDTH-1)
    `define BYTE_DATA_BUS       `BYTE_MSB:`LSB

    /*  word data  */
    `define WORD_DATA_WIDTH     32
    `define WORD_MSB            (`WORD_DATA_WIDTH-1)
    `define WORD_DATA_BUS       `WORD_MSB:`LSB

    /*  word address  */
    `define WORD_ADDR_WIDTH     30
    `define WORD_ADDR_MSB       (`WORD_ADDR_WIDTH-1)
    `define WORD_ADDR_BUS       `WORD_ADDR_MSB:`LSB

    /*  address offset  */
    `define BYTE_OFFSET_WIDTH   2
    `define BYTE_OFFSET_MSB     (`BYTE_OFFSET_WIDTH-1)
    `define BYTE_OFFSET_BUS     `BYTE_OFFSET_MSB:`LSB

    /*  address location  */
    `define WORD_ADDR_LOC       `WORD_ADDR_MSB:`BYTE_OFFSET_WIDTH
    `define BYTE_OFFSET_LOC     `BYTE_OFFSET_MSB:`LSB
    `define BYTE_OFFSET_WORD    2'b00

`endif

Bus/bus_def.v
`ifndef __BUS_DEF__
    `define __BUS_DEF__

    `include "./Global/global_std_def.v"

    /*  bus master num  */
    `define BUS_MASTER_CH           4
    `define BUS_MASTER_INDEX_WIDTH  2

    /*  bus master owner bus  */
    `define BUS_OWNER_BUS           (`BUS_MASTER_INDEX_WIDTH-1):`LSB

    /*  bus owner master  */
    `define BUS_OWNER_MASTER_0      2'h0
    `define BUS_OWNER_MASTER_1      2'h1
    `define BUS_OWNER_MASTER_2      2'h2
    `define BUS_OWNER_MASTER_3      2'h3

    /*  bus slave num  */
    `define BUS_SLAVE_CH            8
    `define BUS_SLAVE_INDEX_WIDTH   3

    /*  bus slave index bus  */
    `define BUS_SLAVE_INDEX_BUS     (`BUS_SLAVE_INDEX_WIDTH-1):`LSB
    /*  bus slave index map to address bus */
    `define BUS_SLAVE_INDEX_LOC     29:27

    /*  bus slave  */
    `define BUS_SLAVE_0     3'h0
    `define BUS_SLAVE_1     3'h1
    `define BUS_SLAVE_2     3'h2
    `define BUS_SLAVE_3     3'h3
    `define BUS_SLAVE_4     3'h4
    `define BUS_SLAVE_5     3'h5
    `define BUS_SLAVE_6     3'h6
    `define BUS_SLAVE_7     3'h7

`endif

Bus/bus_master_mux.v
`include "./Bus/bus_def.v"
`include "./Global/global_std_def.v"

module bus_master_mux(
    /*  master 0  */
    input wire [`WORD_ADDR_BUS] m0_addr,
    input wire m0_as_n,
    input wire m0_rw,
    input wire [`WORD_DATA_BUS] m0_wr_data,
    input wire m0_grnt_n,

    /*  master 1  */
    input wire [`WORD_ADDR_BUS] m1_addr,
    input wire m1_as_n,
    input wire m1_rw,
    input wire [`WORD_DATA_BUS] m1_wr_data,
    input wire m1_grnt_n,

    /*  master 2  */
    input wire [`WORD_ADDR_BUS] m2_addr,
    input wire m2_as_n,
    input wire m2_rw,
    input wire [`WORD_DATA_BUS] m2_wr_data,
    input wire m2_grnt_n,

    /*  master 3  */
    input wire [`WORD_ADDR_BUS] m3_addr,
    input wire m3_as_n,
    input wire m3_rw,
    input wire [`WORD_DATA_BUS] m3_wr_data,
    input wire m3_grnt_n,

    /*  shared signal  */
    output reg [`WORD_ADDR_BUS] s_addr,
    output reg s_as_n,
    output reg s_rw,
    output reg [`WORD_DATA_BUS] s_wr_data
);

    /*  bus master mux  */
    always @(*)
    begin
        if (m0_grnt_n == `ENABLE_)
        begin
            /*  master 0 using bus  */
            s_addr      = m0_addr;
            s_as_n      = m0_as_n;
            s_rw        = m0_rw;
            s_wr_data   = m0_wr_data;
        end
        else if (m1_grnt_n == `ENABLE_)
        begin
            /*  master 1 using bus  */
            s_addr      = m1_addr;
            s_as_n      = m1_as_n;
            s_rw        = m1_rw;
            s_wr_data   = m1_wr_data;
        end
        else if (m2_grnt_n == `ENABLE_)
        begin
            /*  master 2 using bus  */
            s_addr      = m2_addr;
            s_as_n      = m2_as_n;
            s_rw        = m2_rw;
            s_wr_data   = m2_wr_data;
        end
        else if (m3_grnt_n == `ENABLE_)
        begin
            /*  master 3 using bus  */
            s_addr      = m3_addr;
            s_as_n      = m3_as_n;
            s_rw        = m3_rw;
            s_wr_data   = m3_wr_data;
        end
        else
        begin
            /*  default  */
            s_addr      = `WORD_ADDR_WIDTH'h0;
            s_as_n      = `DISABLE_;
            s_rw        = `READ;
            s_wr_data   = `WORD_DATA_WIDTH'h0;
        end
    end

endmodule // bus_master_mux

Bus/testbench/bus_master_mux_tb.v
`timescale 1ns/100ps

`include "./Bus/bus_master_mux.v"
`include "./Global/global_std_def.v"

module bus_master_mux_tb;

    /*  master 0  */
    reg [`WORD_ADDR_BUS] m0_addr = `WORD_ADDR_WIDTH'h12;
    reg m0_as_n = 1'b0;
    reg m0_rw = 1'b0;
    reg [`WORD_DATA_BUS] m0_wr_data = `WORD_DATA_WIDTH'h1234;
    reg m0_grnt_n = `DISABLE_;

    /*  master 1  */
    reg [`WORD_ADDR_BUS] m1_addr = `WORD_ADDR_WIDTH'h34;
    reg m1_as_n = 1'b0;
    reg m1_rw = 1'b1;
    reg [`WORD_DATA_BUS] m1_wr_data = `WORD_DATA_WIDTH'h3456;
    reg m1_grnt_n = `DISABLE_;

    /*  master 2  */
    reg [`WORD_ADDR_BUS] m2_addr = `WORD_ADDR_WIDTH'h56;
    reg m2_as_n = 1'b1;
    reg m2_rw = 1'b0;
    reg [`WORD_DATA_BUS] m2_wr_data = `WORD_DATA_WIDTH'h5678;
    reg m2_grnt_n = `DISABLE_;

    /*  master 3  */
    reg [`WORD_ADDR_BUS] m3_addr = `WORD_ADDR_WIDTH'h78;
    reg m3_as_n = 1'b1;
    reg m3_rw = 1'b1;
    reg [`WORD_DATA_BUS] m3_wr_data = `WORD_DATA_WIDTH'h7890;
    reg m3_grnt_n = `DISABLE_;

    /*  shared signal  */
    wire [`WORD_ADDR_BUS] s_addr;
    wire s_as_n;
    wire s_rw;
    wire [`WORD_DATA_BUS] s_wr_data;

    /*  Instance  */
    bus_master_mux bus_master_mux_01(
        /*  master 0  */
        m0_addr,
        m0_as_n,
        m0_rw,
        m0_wr_data,
        m0_grnt_n,

        /*  master 1  */
        m1_addr,
        m1_as_n,
        m1_rw,
        m1_wr_data,
        m1_grnt_n,

        /*  master 2  */
        m2_addr,
        m2_as_n,
        m2_rw,
        m2_wr_data,
        m2_grnt_n,

        /*  master 3  */
        m3_addr,
        m3_as_n,
        m3_rw,
        m3_wr_data,
        m3_grnt_n,

        /*  shared signal  */
        s_addr,
        s_as_n,
        s_rw,
        s_wr_data
    );

    /*  testbench  */
    initial
    begin
        $dumpfile("bus_master_mux.vcd");
        $dumpvars(0,bus_master_mux_tb);

        // m0
        #50 m0_grnt_n = `ENABLE_;
        // m1
        #50 m0_grnt_n = `DISABLE_;
        #50 m1_grnt_n = `ENABLE_;
        // m2
        #50 m1_grnt_n = `DISABLE_;
        #50 m2_grnt_n = `ENABLE_;
        // m3
        #50 m2_grnt_n = `DISABLE_;
        #50 m3_grnt_n = `ENABLE_;
        // free
        #50 m3_grnt_n = `DISABLE_;

        #100 $finish;
    end

endmodule // bus_master_mux_tb

Bus/testbench/bus_master_mux.vcd
$date
	Mon Nov 11 22:33:12 2019
$end
$version
	Icarus Verilog
$end
$timescale
	100ps
$end
$scope module bus_master_mux_tb $end
$var wire 32 ! s_wr_data [31:0] $end
$var wire 1 " s_rw $end
$var wire 1 # s_as_n $end
$var wire 30 $ s_addr [29:0] $end
$var reg 30 % m0_addr [29:0] $end
$var reg 1 & m0_as_n $end
$var reg 1 ' m0_grnt_n $end
$var reg 1 ( m0_rw $end
$var reg 32 ) m0_wr_data [31:0] $end
$var reg 30 * m1_addr [29:0] $end
$var reg 1 + m1_as_n $end
$var reg 1 , m1_grnt_n $end
$var reg 1 - m1_rw $end
$var reg 32 . m1_wr_data [31:0] $end
$var reg 30 / m2_addr [29:0] $end
$var reg 1 0 m2_as_n $end
$var reg 1 1 m2_grnt_n $end
$var reg 1 2 m2_rw $end
$var reg 32 3 m2_wr_data [31:0] $end
$var reg 30 4 m3_addr [29:0] $end
$var reg 1 5 m3_as_n $end
$var reg 1 6 m3_grnt_n $end
$var reg 1 7 m3_rw $end
$var reg 32 8 m3_wr_data [31:0] $end
$scope module bus_master_mux_01 $end
$var wire 30 9 m0_addr [29:0] $end
$var wire 1 & m0_as_n $end
$var wire 1 ' m0_grnt_n $end
$var wire 1 ( m0_rw $end
$var wire 32 : m0_wr_data [31:0] $end
$var wire 30 ; m1_addr [29:0] $end
$var wire 1 + m1_as_n $end
$var wire 1 , m1_grnt_n $end
$var wire 1 - m1_rw $end
$var wire 32 < m1_wr_data [31:0] $end
$var wire 30 = m2_addr [29:0] $end
$var wire 1 0 m2_as_n $end
$var wire 1 1 m2_grnt_n $end
$var wire 1 2 m2_rw $end
$var wire 32 > m2_wr_data [31:0] $end
$var wire 30 ? m3_addr [29:0] $end
$var wire 1 5 m3_as_n $end
$var wire 1 6 m3_grnt_n $end
$var wire 1 7 m3_rw $end
$var wire 32 @ m3_wr_data [31:0] $end
$var reg 30 A s_addr [29:0] $end
$var reg 1 # s_as_n $end
$var reg 1 " s_rw $end
$var reg 32 B s_wr_data [31:0] $end
$upscope $end
$upscope $end
$enddefinitions $end
#0
$dumpvars
b0 B
b0 A
b111100010010000 @
b1111000 ?
b101011001111000 >
b1010110 =
b11010001010110 <
b110100 ;
b1001000110100 :
b10010 9
b111100010010000 8
17
16
15
b1111000 4
b101011001111000 3
02
11
10
b1010110 /
b11010001010110 .
1-
1,
0+
b110100 *
b1001000110100 )
0(
1'
0&
b10010 %
b0 $
1#
1"
b0 !
$end
#500
b1001000110100 !
b1001000110100 B
0"
0#
b10010 $
b10010 A
0'
#1000
b0 !
b0 B
1"
1#
b0 $
b0 A
1'
#1500
b11010001010110 !
b11010001010110 B
0#
b110100 $
b110100 A
0,
#2000
b0 !
b0 B
1#
b0 $
b0 A
1,
#2500
b101011001111000 !
b101011001111000 B
0"
b1010110 $
b1010110 A
01
#3000
b0 !
b0 B
1"
b0 $
b0 A
11
#3500
b111100010010000 !
b111100010010000 B
b1111000 $
b1111000 A
06
#4000
b0 !
b0 B
b0 $
b0 A
16
