Global/global_std_def.v
`ifndef __GLOBAL_STD_DEF__
    `define __GLOBAL_STD_DEF__

    /*  singal level  */
    `define HIGH        1'b1
    `define LOW         1'b0

    /*  enable & disable  */
    `define DISABLE     1'b0
    `define ENABLE      1'b1
    `define DISABLE_    1'b1
    `define ENABLE_     1'b0

    /*  read & write  */
    `define READ        1'b1
    `define WRITE       1'b0

    /*  Least Significant Bit  */
    `define LSB         0

    /*  byte data  */
    `define BYTE_DATA_WIDTH     8
    `define BYTE_MSB            (`BYTE_DATA_WIDTH-1)
    `define BYTE_DATA_BUS       `BYTE_MSB:`LSB

    /*  word data  */
    `define WORD_DATA_WIDTH     32
    `define WORD_MSB            (`WORD_DATA_WIDTH-1)
    `define WORD_DATA_BUS       `WORD_MSB:`LSB

    /*  word address  */
    `define WORD_ADDR_WIDTH     30
    `define WORD_ADDR_MSB       (`WORD_ADDR_WIDTH-1)
    `define WORD_ADDR_BUS       `WORD_ADDR_MSB:`LSB

    /*  address offset  */
    `define BYTE_OFFSET_WIDTH   2
    `define BYTE_OFFSET_MSB     (`BYTE_OFFSET_WIDTH-1)
    `define BYTE_OFFSET_BUS     `BYTE_OFFSET_MSB:`LSB

    /*  address location  */
    `define WORD_ADDR_LOC       `WORD_ADDR_MSB:`BYTE_OFFSET_WIDTH
    `define BYTE_OFFSET_LOC     `BYTE_OFFSET_MSB:`LSB
    `define BYTE_OFFSET_WORD    2'b00

`endif

Bus/bus_def.v
`ifndef __BUS_DEF__
    `define __BUS_DEF__

    `include "./Global/global_std_def.v"

    /*  bus master num  */
    `define BUS_MASTER_CH           4
    `define BUS_MASTER_INDEX_WIDTH  2

    /*  bus master owner bus  */
    `define BUS_OWNER_BUS           (`BUS_MASTER_INDEX_WIDTH-1):`LSB

    /*  bus owner master  */
    `define BUS_OWNER_MASTER_0      2'h0
    `define BUS_OWNER_MASTER_1      2'h1
    `define BUS_OWNER_MASTER_2      2'h2
    `define BUS_OWNER_MASTER_3      2'h3

    /*  bus slave num  */
    `define BUS_SLAVE_CH            8
    `define BUS_SLAVE_INDEX_WIDTH   3

    /*  bus slave index bus  */
    `define BUS_SLAVE_INDEX_BUS     (`BUS_SLAVE_INDEX_WIDTH-1):`LSB
    /*  bus slave index map to address bus */
    `define BUS_SLAVE_INDEX_LOC     29:27

    /*  bus slave  */
    `define BUS_SLAVE_0     3'h0
    `define BUS_SLAVE_1     3'h1
    `define BUS_SLAVE_2     3'h2
    `define BUS_SLAVE_3     3'h3
    `define BUS_SLAVE_4     3'h4
    `define BUS_SLAVE_5     3'h5
    `define BUS_SLAVE_6     3'h6
    `define BUS_SLAVE_7     3'h7

`endif

Bus/bus_slave_mux.v
`include "./Bus/bus_def.v"
`include "./Global/global_std_def.v"

module bus_slave_mux(
    /*  slave 0  */
    input wire s0_cs_n,
    input wire [`WORD_DATA_BUS] s0_rd_data,
    input wire s0_rdy_n,
    /*  slave 1  */
    input wire s1_cs_n,
    input wire [`WORD_DATA_BUS] s1_rd_data,
    input wire s1_rdy_n,
    /*  slave 2  */
    input wire s2_cs_n,
    input wire [`WORD_DATA_BUS] s2_rd_data,
    input wire s2_rdy_n,
    /*  slave 3  */
    input wire s3_cs_n,
    input wire [`WORD_DATA_BUS] s3_rd_data,
    input wire s3_rdy_n,
    /*  slave 4  */
    input wire s4_cs_n,
    input wire [`WORD_DATA_BUS] s4_rd_data,
    input wire s4_rdy_n,
    /*  slave 5  */
    input wire s5_cs_n,
    input wire [`WORD_DATA_BUS] s5_rd_data,
    input wire s5_rdy_n,
    /*  slave 6  */
    input wire s6_cs_n,
    input wire [`WORD_DATA_BUS] s6_rd_data,
    input wire s6_rdy_n,
    /*  slave 7  */
    input wire s7_cs_n,
    input wire [`WORD_DATA_BUS] s7_rd_data,
    input wire s7_rdy_n,

    /*  master signal  */
    output reg [`WORD_DATA_BUS] m_rd_data,
    output reg m_rdy_n
);

    always @(*)
    begin
        if (s0_cs_n == `ENABLE_)
        begin
           m_rd_data = s0_rd_data;
           m_rdy_n = s0_rdy_n;
        end
        else if (s1_cs_n == `ENABLE_)
        begin
           m_rd_data = s1_rd_data;
           m_rdy_n = s1_rdy_n;
        end
        else if (s2_cs_n == `ENABLE_)
        begin
           m_rd_data = s2_rd_data;
           m_rdy_n = s2_rdy_n;
        end
        else if (s3_cs_n == `ENABLE_)
        begin
           m_rd_data = s3_rd_data;
           m_rdy_n = s3_rdy_n;
        end
        else if (s4_cs_n == `ENABLE_)
        begin
           m_rd_data = s4_rd_data;
           m_rdy_n = s4_rdy_n;
        end
        else if (s5_cs_n == `ENABLE_)
        begin
           m_rd_data = s5_rd_data;
           m_rdy_n = s5_rdy_n;
        end
        else if (s6_cs_n == `ENABLE_)
        begin
           m_rd_data = s6_rd_data;
           m_rdy_n = s6_rdy_n;
        end
        else if (s7_cs_n == `ENABLE_)
        begin
           m_rd_data = s7_rd_data;
           m_rdy_n = s7_rdy_n;
        end
        else
        begin
            m_rd_data = `WORD_DATA_WIDTH'h0;
            m_rdy_n = `DISABLE_;
        end
    end

endmodule // bus_slave_mux

Bus/bus_addr_dec.v
`include "./Bus/bus_def.v"
`include "./Global/global_std_def.v"

// book is wrong??? (p74,table:1-19,address)

module bus_addr_dec(
    /*  shared address bus  */
    input wire [`WORD_ADDR_BUS] s_addr,

    /*  chip select  */
    output reg s0_cs_n,
    output reg s1_cs_n,
    output reg s2_cs_n,
    output reg s3_cs_n,
    output reg s4_cs_n,
    output reg s5_cs_n,
    output reg s6_cs_n,
    output reg s7_cs_n
);
    /*  address index  */
    wire [`BUS_SLAVE_INDEX_BUS] s_index;

    assign s_index = s_addr[`BUS_SLAVE_INDEX_LOC];

    always @(*)
    begin
    
        s0_cs_n = `DISABLE_;
        s1_cs_n = `DISABLE_;
        s2_cs_n = `DISABLE_;
        s3_cs_n = `DISABLE_;
        s4_cs_n = `DISABLE_;
        s5_cs_n = `DISABLE_;
        s6_cs_n = `DISABLE_;
        s7_cs_n = `DISABLE_;

        case(s_index)
            `BUS_SLAVE_0: begin s0_cs_n = `ENABLE_; end
            `BUS_SLAVE_1: begin s1_cs_n = `ENABLE_; end
            `BUS_SLAVE_2: begin s2_cs_n = `ENABLE_; end
            `BUS_SLAVE_3: begin s3_cs_n = `ENABLE_; end
            `BUS_SLAVE_4: begin s4_cs_n = `ENABLE_; end
            `BUS_SLAVE_5: begin s5_cs_n = `ENABLE_; end
            `BUS_SLAVE_6: begin s6_cs_n = `ENABLE_; end
            `BUS_SLAVE_7: begin s7_cs_n = `ENABLE_; end
        endcase
    end

endmodule // bus_addr_dec

Global/global_cfg_def.v
`ifndef __GLOBAL_CFG_DEF__
    `define __GLOBAL_CFG_DEF__

    /*  choose RESET polarity  */
    // `define POSITIVE_RESET
    `define NEGATIVE_RESET

    /*  choose MEMORY polarity  */
    `define POSITIVE_MEMORY
    // `define NEGATIVE_MRMORY

    /*  Enable I/O Modules  */
    // `define IMPLEMENT_TIMER
    // `define IMPLEMENT_UART
    // `define IMPLEMENT_GPIO

    /*  generate RESET_ENABLE & RESET_DISABLE & RESET_EDGE */
    // book is wrong???
    // `ifdef POSITIVE_RESET
    //     `define RESET_EDGE      posedge
    //     `define RESET_ENABLE    1'b0
    //     `define RESET_DISABLE   1'b1
    // `elif NEGATIVE_RESET
        `define RESET_EDGE      negedge
        `define RESET_ENABLE    1'b1
        `define RESET_DISABLE   1'b0
    // `endif
    

    /*  generate MEM_ENABLE & MEM_DISABLE  */
    // `ifdef POSITIVE_MEMORY
        `define MEM_ENABLE    1'b1
        `define MEM_DISABLE   1'b0
    // `elif NEGATIVE_MRMORY
    //     `define MEM_ENABLE    1'b0
    //     `define MEM_DISABLE   1'b1
    // `endif

`endif

Bus/bus_master_mux.v
`include "./Bus/bus_def.v"
`include "./Global/global_std_def.v"
`include "./Global/global_cfg_def.v"

module bus_master_mux(
    /*  master 0  */
    input wire [`WORD_ADDR_BUS] m0_addr,
    input wire m0_as_n,
    input wire m0_rw,
    input wire [`WORD_DATA_BUS] m0_wr_data,
    input wire m0_grnt_n,

    /*  master 1  */
    input wire [`WORD_ADDR_BUS] m1_addr,
    input wire m1_as_n,
    input wire m1_rw,
    input wire [`WORD_DATA_BUS] m1_wr_data,
    input wire m1_grnt_n,

    /*  master 2  */
    input wire [`WORD_ADDR_BUS] m2_addr,
    input wire m2_as_n,
    input wire m2_rw,
    input wire [`WORD_DATA_BUS] m2_wr_data,
    input wire m2_grnt_n,

    /*  master 3  */
    input wire [`WORD_ADDR_BUS] m3_addr,
    input wire m3_as_n,
    input wire m3_rw,
    input wire [`WORD_DATA_BUS] m3_wr_data,
    input wire m3_grnt_n,

    /*  shared signal  */
    output reg [`WORD_ADDR_BUS] s_addr,
    output reg s_as_n,
    output reg s_rw,
    output reg [`WORD_DATA_BUS] s_wr_data
);




endmodule // bus_master_mux

Bus/bus_arbiter.v
`include "./Bus/bus_def.v"
`include "./Global/global_std_def.v"
`include "./Global/global_cfg_def.v"

module bus_arbiter(
    /*  clock & reset  */
    input wire clk,
    input wire reset,

    /*  bus master's request & grant buses */
    input wire m0_req_n,
    output reg m0_grnt_n,

    input wire m1_req_n,
    output reg m1_grnt_n,

    input wire m2_req_n,
    output reg m2_grnt_n,
    
    input wire m3_req_n,
    output reg m3_grnt_n
);

    reg [`BUS_OWNER_BUS] owner;

    /*  grant usage of bus  */
    always@(*)
    begin
        m0_grnt_n = `DISABLE_;
        m1_grnt_n = `DISABLE_;
        m2_grnt_n = `DISABLE_;
        m3_grnt_n = `DISABLE_;
        case (owner)
            `BUS_OWNER_MASTER_0: begin m0_grnt_n = `ENABLE_; end
            `BUS_OWNER_MASTER_1: begin m1_grnt_n = `ENABLE_; end
            `BUS_OWNER_MASTER_2: begin m2_grnt_n = `ENABLE_; end
            `BUS_OWNER_MASTER_3: begin m3_grnt_n = `ENABLE_; end
        endcase
    end

    /*  arbiter of usage of bus  */
    always@(posedge clk or `RESET_EDGE reset)
    begin
        if (reset == `RESET_DISABLE)    // book is wrong ???
        begin
            /*  reset  */
            owner <= #1 `BUS_OWNER_MASTER_0;
        end
        else
        begin
            /*  arbiter polling  */
            case (owner)
                `BUS_OWNER_MASTER_0:
                begin
                    if (m0_req_n == `ENABLE_)
                    begin
                        owner <= #1 `BUS_OWNER_MASTER_0;
                    end
                    else if(m1_req_n == `ENABLE_)
                    begin
                        owner <= #1 `BUS_OWNER_MASTER_1;
                    end
                    else if(m2_req_n == `ENABLE_)
                    begin
                        owner <= #1 `BUS_OWNER_MASTER_2;
                    end
                    else if(m3_req_n == `ENABLE_)
                    begin
                        owner <= #1 `BUS_OWNER_MASTER_3;
                    end
                end

                `BUS_OWNER_MASTER_1:
                begin
                    if (m1_req_n == `ENABLE_)
                    begin
                        owner <= #1 `BUS_OWNER_MASTER_1;
                    end
                    else if(m2_req_n == `ENABLE_)
                    begin
                        owner <= #1 `BUS_OWNER_MASTER_2;
                    end
                    else if(m3_req_n == `ENABLE_)
                    begin
                        owner <= #1 `BUS_OWNER_MASTER_3;
                    end
                    else if(m0_req_n == `ENABLE_)
                    begin
                        owner <= #1 `BUS_OWNER_MASTER_0;
                    end
                end

                `BUS_OWNER_MASTER_2:
                begin
                    if (m2_req_n == `ENABLE_)
                    begin
                        owner <= #1 `BUS_OWNER_MASTER_2;
                    end
                    else if(m3_req_n == `ENABLE_)
                    begin
                        owner <= #1 `BUS_OWNER_MASTER_3;
                    end
                    else if(m0_req_n == `ENABLE_)
                    begin
                        owner <= #1 `BUS_OWNER_MASTER_0;
                    end
                    else if(m1_req_n == `ENABLE_)
                    begin
                        owner <= #1 `BUS_OWNER_MASTER_1;
                    end
                end

                `BUS_OWNER_MASTER_3:
                begin
                    if (m3_req_n == `ENABLE_)
                    begin
                        owner <= #1 `BUS_OWNER_MASTER_3;
                    end
                    else if(m0_req_n == `ENABLE_)
                    begin
                        owner <= #1 `BUS_OWNER_MASTER_0;
                    end
                    else if(m1_req_n == `ENABLE_)
                    begin
                        owner <= #1 `BUS_OWNER_MASTER_1;
                    end
                    else if(m2_req_n == `ENABLE_)
                    begin
                        owner <= #1 `BUS_OWNER_MASTER_2;
                    end
                end
            endcase
        end

    end
endmodule // bus_arbiterf

Bus/bus_top.v
`include "./Bus/bus_def.v"
`include "./Global/global_std_def.v"

`include "./Bus/bus_arbiter.v"
`include "./Bus/bus_master_mux.v"
`include "./Bus/bus_addr_dec.v"
`include "./Bus/bus_slave_mux.v"

module bus_top(
    /*  clock & reset  */
    input wire clk,
    input wire reset,

    /*  master 0-3  */
    input wire m0_req_n,
    output wire m0_grnt_n,
    input wire [`WORD_ADDR_BUS] m0_addr,
    input wire m0_as_n,
    input wire m0_rw,
    input wire [`WORD_DATA_BUS] m0_wr_data,

    input wire m1_req_n,
    output wire m1_grnt_n,
    input wire [`WORD_ADDR_BUS] m1_addr,
    input wire m1_as_n,
    input wire m1_rw,
    input wire [`WORD_DATA_BUS] m1_wr_data,

    input wire m2_req_n,
    output wire m2_grnt_n,
    input wire [`WORD_ADDR_BUS] m2_addr,
    input wire m2_as_n,
    input wire m2_rw,
    input wire [`WORD_DATA_BUS] m2_wr_data,

    input wire m3_req_n,
    output wire m3_grnt_n,
    input wire [`WORD_ADDR_BUS] m3_addr,
    input wire m3_as_n,
    input wire m3_rw,
    input wire [`WORD_DATA_BUS] m3_wr_data,

    /*  master shared signal  */
    output wire [`WORD_DATA_BUS] m_rd_data,
    output wire m_rdy_n,

    /*  slave 0-7  */
    output wire s0_cs_n,
    input wire [`WORD_DATA_BUS] s0_rd_data,
    input wire s0_rdy_n,

    output wire s1_cs_n,
    input wire [`WORD_DATA_BUS] s1_rd_data,
    input wire s1_rdy_n,

    output wire s2_cs_n,
    input wire [`WORD_DATA_BUS] s2_rd_data,
    input wire s2_rdy_n,
    
    output wire s3_cs_n,
    input wire [`WORD_DATA_BUS] s3_rd_data,
    input wire s3_rdy_n,
    
    output wire s4_cs_n,
    input wire [`WORD_DATA_BUS] s4_rd_data,
    input wire s4_rdy_n,
    
    output wire s5_cs_n,
    input wire [`WORD_DATA_BUS] s5_rd_data,
    input wire s5_rdy_n,
    
    output wire s6_cs_n,
    input wire [`WORD_DATA_BUS] s6_rd_data,
    input wire s6_rdy_n,
    
    output wire s7_cs_n,
    input wire [`WORD_DATA_BUS] s7_rd_data,
    input wire s7_rdy_n,

    /*  slave shared signal  */
    output wire [`WORD_ADDR_BUS] s_addr,
    output wire s_as_n,
    output wire s_rw,
    output wire [`WORD_DATA_BUS] s_wr_data
);

    bus_arbiter bus_arbiter_01(
        clk,
        reset,
        m0_req_n,
        m0_grnt_n,
        m1_req_n,
        m1_grnt_n,
        m2_req_n,
        m2_grnt_n,
        m3_req_n,
        m3_grnt_n
    );

    bus_master_mux bus_master_mux_01(
        m0_addr,
        m0_as_n,
        m0_rw,
        m0_wr_data,
        m0_grnt_n,
        m1_addr,
        m1_as_n,
        m1_rw,
        m1_wr_data,
        m1_grnt_n,
        m2_addr,
        m2_as_n,
        m2_rw,
        m2_wr_data,
        m2_grnt_n,
        m3_addr,
        m3_as_n,
        m3_rw,
        m3_wr_data,
        m3_grnt_n,
        s_addr,
        s_as_n,
        s_rw,
        s_wr_data
    );

    bus_addr_dec bus_addr_dec_01(
        s_addr,
        s0_cs_n,
        s1_cs_n,
        s2_cs_n,
        s3_cs_n,
        s4_cs_n,
        s5_cs_n,
        s6_cs_n,
        s7_cs_n
    );

    bus_slave_mux bus_slave_mux_01(
        s0_cs_n,
        s0_rd_data,
        s0_rdy_n,
        s1_cs_n,
        s1_rd_data,
        s1_rdy_n,
        s2_cs_n,
        s2_rd_data,
        s2_rdy_n,
        s3_cs_n,
        s3_rd_data,
        s3_rdy_n,
        s4_cs_n,
        s4_rd_data,
        s4_rdy_n,
        s5_cs_n,
        s5_rd_data,
        s5_rdy_n,
        s6_cs_n,
        s6_rd_data,
        s6_rdy_n,
        s7_cs_n,
        s7_rd_data,
        s7_rdy_n,
        m_rd_data,
        m_rdy_n
    );

endmodule // bus_top

Bus/testbench/bus_top_tb.v
`timescale 1ns/100ps

`include "./Bus/bus_top.v"
`include "./Global/global_std_def.v"

module bus_top_tb;

    /*  clock & reset  */
    reg clk = `LOW;
    reg reset = `RESET_DISABLE;

    /*  master 0-3  */
    reg m0_req_n = `DISABLE_;
    wire m0_grnt_n;
    reg [`WORD_ADDR_BUS] m0_addr;
    reg m0_as_n = `DISABLE_;
    reg m0_rw;
    reg [`WORD_DATA_BUS] m0_wr_data;

    reg m1_req_n = `DISABLE_;
    wire m1_grnt_n;
    reg [`WORD_ADDR_BUS] m1_addr;
    reg m1_as_n = `DISABLE_;
    reg m1_rw;
    reg [`WORD_DATA_BUS] m1_wr_data;

    reg m2_req_n = `DISABLE_;
    wire m2_grnt_n;
    reg [`WORD_ADDR_BUS] m2_addr;
    reg m2_as_n = `DISABLE_;
    reg m2_rw;
    reg [`WORD_DATA_BUS] m2_wr_data;

    reg m3_req_n = `DISABLE_;
    wire m3_grnt_n;
    reg [`WORD_ADDR_BUS] m3_addr;
    reg m3_as_n = `DISABLE_;
    reg m3_rw;
    reg [`WORD_DATA_BUS] m3_wr_data;

    /*  master shared signal  */
    wire [`WORD_DATA_BUS] m_rd_data;
    wire m_rdy_n;
    /*  slave 0-7  */
    wire s0_cs_n;
    reg [`WORD_DATA_BUS] s0_rd_data;
    reg s0_rdy_n = `DISABLE_;
    wire s1_cs_n;
    reg [`WORD_DATA_BUS] s1_rd_data;
    reg s1_rdy_n = `DISABLE_;
    wire s2_cs_n;
    reg [`WORD_DATA_BUS] s2_rd_data;
    reg s2_rdy_n = `DISABLE_;
    wire s3_cs_n;
    reg [`WORD_DATA_BUS] s3_rd_data;
    reg s3_rdy_n = `DISABLE_;
    wire s4_cs_n;
    reg [`WORD_DATA_BUS] s4_rd_data;
    reg s4_rdy_n = `DISABLE_;
    wire s5_cs_n;
    reg [`WORD_DATA_BUS] s5_rd_data;
    reg s5_rdy_n = `DISABLE_;
    wire s6_cs_n;
    reg [`WORD_DATA_BUS] s6_rd_data;
    reg s6_rdy_n = `DISABLE_;
    wire s7_cs_n;
    reg [`WORD_DATA_BUS] s7_rd_data;
    reg s7_rdy_n = `DISABLE_;
    /*  slave shared signal  */
    wire [`WORD_ADDR_BUS] s_addr;
    wire s_as_n;
    wire s_rw;
    wire [`WORD_DATA_BUS] s_wr_data;


    bus_top bus_top_01(
        /*  clock & reset  */
        clk,
        reset,

        /*  master 0-3  */
        m0_req_n,
        m0_grnt_n,
        m0_addr,
        m0_as_n,
        m0_rw,
        m0_wr_data,

        m1_req_n,
        m1_grnt_n,
        m1_addr,
        m1_as_n,
        m1_rw,
        m1_wr_data,

        m2_req_n,
        m2_grnt_n,
        m2_addr,
        m2_as_n,
        m2_rw,
        m2_wr_data,

        m3_req_n,
        m3_grnt_n,
        m3_addr,
        m3_as_n,
        m3_rw,
        m3_wr_data,

        /*  master shared signal  */
        m_rd_data,
        m_rdy_n,

        /*  slave 0-7  */
        s0_cs_n,
        s0_rd_data,
        s0_rdy_n,

        s1_cs_n,
        s1_rd_data,
        s1_rdy_n,

        s2_cs_n,
        s2_rd_data,
        s2_rdy_n,
        
        s3_cs_n,
        s3_rd_data,
        s3_rdy_n,
        
        s4_cs_n,
        s4_rd_data,
        s4_rdy_n,
        
        s5_cs_n,
        s5_rd_data,
        s5_rdy_n,
        
        s6_cs_n,
        s6_rd_data,
        s6_rdy_n,
        
        s7_cs_n,
        s7_rd_data,
        s7_rdy_n,

        /*  slave shared signal  */
        s_addr,
        s_as_n,
        s_rw,
        s_wr_data
    );


    /*  clock  */
    always
        #10 clk = ~clk;

    /*  testbench  */
    initial
    begin
        $dumpfile("bus_top.vcd");
        $dumpvars(0,bus_top_tb);

        // test for reset
        #50 reset = `RESET_ENABLE;
        #50 m3_req_n = `ENABLE_;
        #50 reset = `RESET_DISABLE;
        #50 m3_req_n = `DISABLE_;
        #50 reset = `RESET_ENABLE;


        // m0 request usage of bus
        #100 m0_req_n = `ENABLE_;
        m0_addr = `WORD_ADDR_WIDTH'h1000_0000;
        m0_as_n = `ENABLE_;
        m0_rw = `WRITE;
        m0_wr_data = `WORD_DATA_WIDTH'h1234;

        // when m0 using bus, m1 request
        #100 m0_as_n = `DISABLE_;
        
        m1_req_n = `ENABLE_;
        m1_addr = `WORD_ADDR_WIDTH'h3F00_0000;
        m1_as_n = `ENABLE_;
        m1_rw = `READ;
        s7_rd_data = `WORD_DATA_WIDTH'h5678;
        s7_rdy_n = `ENABLE_;

        

        // m0 request finished, m1 will use the bus
        #100 m1_as_n = `DISABLE_;
        s7_rdy_n = `DISABLE_;

        m0_req_n = `DISABLE_;

        // m1 request finished
        #100 m1_req_n = `DISABLE_;

        #100 $finish;
    end


endmodule // bus_top_tb

Bus/testbench/bus_top.vcd
$date
	Wed Nov 13 09:07:09 2019
$end
$version
	Icarus Verilog
$end
$timescale
	100ps
$end
$scope module bus_top_tb $end
$var wire 32 ! s_wr_data [31:0] $end
$var wire 1 " s_rw $end
$var wire 1 # s_as_n $end
$var wire 30 $ s_addr [29:0] $end
$var wire 1 % s7_cs_n $end
$var wire 1 & s6_cs_n $end
$var wire 1 ' s5_cs_n $end
$var wire 1 ( s4_cs_n $end
$var wire 1 ) s3_cs_n $end
$var wire 1 * s2_cs_n $end
$var wire 1 + s1_cs_n $end
$var wire 1 , s0_cs_n $end
$var wire 1 - m_rdy_n $end
$var wire 32 . m_rd_data [31:0] $end
$var wire 1 / m3_grnt_n $end
$var wire 1 0 m2_grnt_n $end
$var wire 1 1 m1_grnt_n $end
$var wire 1 2 m0_grnt_n $end
$var reg 1 3 clk $end
$var reg 30 4 m0_addr [29:0] $end
$var reg 1 5 m0_as_n $end
$var reg 1 6 m0_req_n $end
$var reg 1 7 m0_rw $end
$var reg 32 8 m0_wr_data [31:0] $end
$var reg 30 9 m1_addr [29:0] $end
$var reg 1 : m1_as_n $end
$var reg 1 ; m1_req_n $end
$var reg 1 < m1_rw $end
$var reg 32 = m1_wr_data [31:0] $end
$var reg 30 > m2_addr [29:0] $end
$var reg 1 ? m2_as_n $end
$var reg 1 @ m2_req_n $end
$var reg 1 A m2_rw $end
$var reg 32 B m2_wr_data [31:0] $end
$var reg 30 C m3_addr [29:0] $end
$var reg 1 D m3_as_n $end
$var reg 1 E m3_req_n $end
$var reg 1 F m3_rw $end
$var reg 32 G m3_wr_data [31:0] $end
$var reg 1 H reset $end
$var reg 32 I s0_rd_data [31:0] $end
$var reg 1 J s0_rdy_n $end
$var reg 32 K s1_rd_data [31:0] $end
$var reg 1 L s1_rdy_n $end
$var reg 32 M s2_rd_data [31:0] $end
$var reg 1 N s2_rdy_n $end
$var reg 32 O s3_rd_data [31:0] $end
$var reg 1 P s3_rdy_n $end
$var reg 32 Q s4_rd_data [31:0] $end
$var reg 1 R s4_rdy_n $end
$var reg 32 S s5_rd_data [31:0] $end
$var reg 1 T s5_rdy_n $end
$var reg 32 U s6_rd_data [31:0] $end
$var reg 1 V s6_rdy_n $end
$var reg 32 W s7_rd_data [31:0] $end
$var reg 1 X s7_rdy_n $end
$scope module bus_top_01 $end
$var wire 1 3 clk $end
$var wire 30 Y m0_addr [29:0] $end
$var wire 1 5 m0_as_n $end
$var wire 1 6 m0_req_n $end
$var wire 1 7 m0_rw $end
$var wire 32 Z m0_wr_data [31:0] $end
$var wire 30 [ m1_addr [29:0] $end
$var wire 1 : m1_as_n $end
$var wire 1 ; m1_req_n $end
$var wire 1 < m1_rw $end
$var wire 32 \ m1_wr_data [31:0] $end
$var wire 30 ] m2_addr [29:0] $end
$var wire 1 ? m2_as_n $end
$var wire 1 @ m2_req_n $end
$var wire 1 A m2_rw $end
$var wire 32 ^ m2_wr_data [31:0] $end
$var wire 30 _ m3_addr [29:0] $end
$var wire 1 D m3_as_n $end
$var wire 1 E m3_req_n $end
$var wire 1 F m3_rw $end
$var wire 32 ` m3_wr_data [31:0] $end
$var wire 1 H reset $end
$var wire 32 a s0_rd_data [31:0] $end
$var wire 1 J s0_rdy_n $end
$var wire 32 b s1_rd_data [31:0] $end
$var wire 1 L s1_rdy_n $end
$var wire 32 c s2_rd_data [31:0] $end
$var wire 1 N s2_rdy_n $end
$var wire 32 d s3_rd_data [31:0] $end
$var wire 1 P s3_rdy_n $end
$var wire 32 e s4_rd_data [31:0] $end
$var wire 1 R s4_rdy_n $end
$var wire 32 f s5_rd_data [31:0] $end
$var wire 1 T s5_rdy_n $end
$var wire 32 g s6_rd_data [31:0] $end
$var wire 1 V s6_rdy_n $end
$var wire 32 h s7_rd_data [31:0] $end
$var wire 1 X s7_rdy_n $end
$var wire 32 i s_wr_data [31:0] $end
$var wire 1 " s_rw $end
$var wire 1 # s_as_n $end
$var wire 30 j s_addr [29:0] $end
$var wire 1 % s7_cs_n $end
$var wire 1 & s6_cs_n $end
$var wire 1 ' s5_cs_n $end
$var wire 1 ( s4_cs_n $end
$var wire 1 ) s3_cs_n $end
$var wire 1 * s2_cs_n $end
$var wire 1 + s1_cs_n $end
$var wire 1 , s0_cs_n $end
$var wire 1 - m_rdy_n $end
$var wire 32 k m_rd_data [31:0] $end
$var wire 1 / m3_grnt_n $end
$var wire 1 0 m2_grnt_n $end
$var wire 1 1 m1_grnt_n $end
$var wire 1 2 m0_grnt_n $end
$scope module bus_addr_dec_01 $end
$var wire 3 l s_index [2:0] $end
$var wire 30 m s_addr [29:0] $end
$var reg 1 , s0_cs_n $end
$var reg 1 + s1_cs_n $end
$var reg 1 * s2_cs_n $end
$var reg 1 ) s3_cs_n $end
$var reg 1 ( s4_cs_n $end
$var reg 1 ' s5_cs_n $end
$var reg 1 & s6_cs_n $end
$var reg 1 % s7_cs_n $end
$upscope $end
$scope module bus_arbiter_01 $end
$var wire 1 3 clk $end
$var wire 1 6 m0_req_n $end
$var wire 1 ; m1_req_n $end
$var wire 1 @ m2_req_n $end
$var wire 1 E m3_req_n $end
$var wire 1 H reset $end
$var reg 1 2 m0_grnt_n $end
$var reg 1 1 m1_grnt_n $end
$var reg 1 0 m2_grnt_n $end
$var reg 1 / m3_grnt_n $end
$var reg 2 n owner [1:0] $end
$upscope $end
$scope module bus_master_mux_01 $end
$var wire 30 o m0_addr [29:0] $end
$var wire 1 5 m0_as_n $end
$var wire 1 2 m0_grnt_n $end
$var wire 1 7 m0_rw $end
$var wire 32 p m0_wr_data [31:0] $end
$var wire 30 q m1_addr [29:0] $end
$var wire 1 : m1_as_n $end
$var wire 1 1 m1_grnt_n $end
$var wire 1 < m1_rw $end
$var wire 32 r m1_wr_data [31:0] $end
$var wire 30 s m2_addr [29:0] $end
$var wire 1 ? m2_as_n $end
$var wire 1 0 m2_grnt_n $end
$var wire 1 A m2_rw $end
$var wire 32 t m2_wr_data [31:0] $end
$var wire 30 u m3_addr [29:0] $end
$var wire 1 D m3_as_n $end
$var wire 1 / m3_grnt_n $end
$var wire 1 F m3_rw $end
$var wire 32 v m3_wr_data [31:0] $end
$var reg 30 w s_addr [29:0] $end
$var reg 1 # s_as_n $end
$var reg 1 " s_rw $end
$var reg 32 x s_wr_data [31:0] $end
$upscope $end
$scope module bus_slave_mux_01 $end
$var wire 1 , s0_cs_n $end
$var wire 32 y s0_rd_data [31:0] $end
$var wire 1 J s0_rdy_n $end
$var wire 1 + s1_cs_n $end
$var wire 32 z s1_rd_data [31:0] $end
$var wire 1 L s1_rdy_n $end
$var wire 1 * s2_cs_n $end
$var wire 32 { s2_rd_data [31:0] $end
$var wire 1 N s2_rdy_n $end
$var wire 1 ) s3_cs_n $end
$var wire 32 | s3_rd_data [31:0] $end
$var wire 1 P s3_rdy_n $end
$var wire 1 ( s4_cs_n $end
$var wire 32 } s4_rd_data [31:0] $end
$var wire 1 R s4_rdy_n $end
$var wire 1 ' s5_cs_n $end
$var wire 32 ~ s5_rd_data [31:0] $end
$var wire 1 T s5_rdy_n $end
$var wire 1 & s6_cs_n $end
$var wire 32 !" s6_rd_data [31:0] $end
$var wire 1 V s6_rdy_n $end
$var wire 1 % s7_cs_n $end
$var wire 32 "" s7_rd_data [31:0] $end
$var wire 1 X s7_rdy_n $end
$var reg 32 #" m_rd_data [31:0] $end
$var reg 1 - m_rdy_n $end
$upscope $end
$upscope $end
$upscope $end
$enddefinitions $end
#0
$dumpvars
bx #"
bx ""
bx !"
bx ~
bx }
bx |
bx {
bx z
bx y
b0 x
b0 w
bx v
bx u
bx t
bx s
bx r
bx q
bx p
bx o
bx n
b0 m
b0 l
bx k
b0 j
b0 i
bx h
bx g
bx f
bx e
bx d
bx c
bx b
bx a
bx `
bx _
bx ^
bx ]
bx \
bx [
bx Z
bx Y
1X
bx W
1V
bx U
1T
bx S
1R
bx Q
1P
bx O
1N
bx M
1L
bx K
1J
bx I
1H
bx G
xF
1E
1D
bx C
bx B
xA
1@
1?
bx >
bx =
x<
1;
1:
bx 9
bx 8
x7
16
15
bx 4
03
x2
x1
x0
x/
bx .
1-
0,
1+
1*
1)
1(
1'
1&
1%
b0 $
1#
1"
b0 !
$end
#100
13
#110
b0 .
b0 k
b0 #"
1,
bx l
bx !
bx i
bx x
x"
bx $
bx j
bx m
bx w
1/
10
11
02
b0 n
#200
03
#300
13
#400
03
#500
13
0H
#600
03
#700
13
#800
03
#900
13
#1000
03
0E
#1100
13
#1110
0/
12
b11 n
#1200
03
#1300
13
#1400
03
#1500
13
1H
#1510
02
1/
b0 n
#1600
03
#1700
13
#1800
03
#1900
13
#2000
03
1E
#2100
13
#2200
03
#2300
13
#2400
03
#2500
13
0H
#2600
03
#2700
13
#2800
03
#2900
13
#3000
03
#3100
13
#3200
03
#3300
13
#3400
03
