Global/global_std_def.v
`ifndef __GLOBAL_STD_DEF__
    `define __GLOBAL_STD_DEF__

    /*  singal level  */
    `define HIGH        1'b1
    `define LOW         1'b0

    /*  enable & disable  */
    `define DISABLE     1'b0
    `define ENABLE      1'b1
    `define DISABLE_    1'b1
    `define ENABLE_     1'b0

    /*  read & write  */
    `define READ        1'b1
    `define WRITE       1'b0

    /*  Least Significant Bit  */
    `define LSB         0

    /*  byte data  */
    `define BYTE_DATA_WIDTH     8
    `define BYTE_MSB            (`BYTE_DATA_WIDTH-1)
    `define BYTE_DATA_BUS       `BYTE_MSB:`LSB

    /*  word data  */
    `define WORD_DATA_WIDTH     32
    `define WORD_MSB            (`WORD_DATA_WIDTH-1)
    `define WORD_DATA_BUS       `WORD_MSB:`LSB

    /*  word address  */
    `define WORD_ADDR_WIDTH     30
    `define WORD_ADDR_MSB       (`WORD_ADDR_WIDTH-1)
    `define WORD_ADDR_BUS       `WORD_ADDR_MSB:`LSB

    /*  address offset  */
    `define BYTE_OFFSET_WIDTH   2
    `define BYTE_OFFSET_MSB     (`BYTE_OFFSET_WIDTH-1)
    `define BYTE_OFFSET_BUS     `BYTE_OFFSET_MSB:`LSB

    /*  address location  */
    `define WORD_ADDR_LOC       `WORD_ADDR_MSB:`BYTE_OFFSET_WIDTH
    `define BYTE_OFFSET_LOC     `BYTE_OFFSET_MSB:`LSB
    `define BYTE_OFFSET_WORD    2'b00

`endif

Bus/bus_def.v
`ifndef __BUS_DEF__
    `define __BUS_DEF__

    `include "./Global/global_std_def.v"

    /*  bus master num  */
    `define BUS_MASTER_CH           4
    `define BUS_MASTER_INDEX_WIDTH  2

    /*  bus master owner bus  */
    `define BUS_OWNER_BUS           (`BUS_MASTER_INDEX_WIDTH-1):`LSB

    /*  bus owner master  */
    `define BUS_OWNER_MASTER_0      2'h0
    `define BUS_OWNER_MASTER_1      2'h1
    `define BUS_OWNER_MASTER_2      2'h2
    `define BUS_OWNER_MASTER_3      2'h3

    /*  bus slave num  */
    `define BUS_SLAVE_CH            8
    `define BUS_SLAVE_INDEX_WIDTH   3

    /*  bus slave index bus  */
    `define BUS_SLAVE_INDEX_BUS     (`BUS_SLAVE_INDEX_WIDTH-1):`LSB
    /*  bus slave index map to address bus */
    `define BUS_SLAVE_INDEX_LOC     29:27

    /*  bus slave  */
    `define BUS_SLAVE_0     3'h0
    `define BUS_SLAVE_1     3'h1
    `define BUS_SLAVE_2     3'h2
    `define BUS_SLAVE_3     3'h3
    `define BUS_SLAVE_4     3'h4
    `define BUS_SLAVE_5     3'h5
    `define BUS_SLAVE_6     3'h6
    `define BUS_SLAVE_7     3'h7

`endif

Bus/bus_slave_mux.v
`include "./Bus/bus_def.v"
`include "./Global/global_std_def.v"

module bus_slave_mux(
    /*  slave 0  */
    input wire s0_cs_n,
    input wire [`WORD_DATA_BUS] s0_rd_data,
    input wire s0_rdy_n,
    /*  slave 1  */
    input wire s1_cs_n,
    input wire [`WORD_DATA_BUS] s1_rd_data,
    input wire s1_rdy_n,
    /*  slave 2  */
    input wire s2_cs_n,
    input wire [`WORD_DATA_BUS] s2_rd_data,
    input wire s2_rdy_n,
    /*  slave 3  */
    input wire s3_cs_n,
    input wire [`WORD_DATA_BUS] s3_rd_data,
    input wire s3_rdy_n,
    /*  slave 4  */
    input wire s4_cs_n,
    input wire [`WORD_DATA_BUS] s4_rd_data,
    input wire s4_rdy_n,
    /*  slave 5  */
    input wire s5_cs_n,
    input wire [`WORD_DATA_BUS] s5_rd_data,
    input wire s5_rdy_n,
    /*  slave 6  */
    input wire s6_cs_n,
    input wire [`WORD_DATA_BUS] s6_rd_data,
    input wire s6_rdy_n,
    /*  slave 7  */
    input wire s7_cs_n,
    input wire [`WORD_DATA_BUS] s7_rd_data,
    input wire s7_rdy_n,

    /*  master signal  */
    output reg [`WORD_DATA_BUS] m_rd_data,
    output reg m_rdy_n
);

    always @(*)
    begin
        if (s0_cs_n == `ENABLE_)
        begin
           m_rd_data = s0_rd_data;
           m_rdy_n = s0_rdy_n;
        end
        else if (s1_cs_n == `ENABLE_)
        begin
           m_rd_data = s1_rd_data;
           m_rdy_n = s1_rdy_n;
        end
        else if (s2_cs_n == `ENABLE_)
        begin
           m_rd_data = s2_rd_data;
           m_rdy_n = s2_rdy_n;
        end
        else if (s3_cs_n == `ENABLE_)
        begin
           m_rd_data = s3_rd_data;
           m_rdy_n = s3_rdy_n;
        end
        else if (s4_cs_n == `ENABLE_)
        begin
           m_rd_data = s4_rd_data;
           m_rdy_n = s4_rdy_n;
        end
        else if (s5_cs_n == `ENABLE_)
        begin
           m_rd_data = s5_rd_data;
           m_rdy_n = s5_rdy_n;
        end
        else if (s6_cs_n == `ENABLE_)
        begin
           m_rd_data = s6_rd_data;
           m_rdy_n = s6_rdy_n;
        end
        else if (s7_cs_n == `ENABLE_)
        begin
           m_rd_data = s7_rd_data;
           m_rdy_n = s7_rdy_n;
        end
        else
        begin
            m_rd_data = `WORD_DATA_WIDTH'h0;
            m_rdy_n = `DISABLE_;
        end
    end

endmodule // bus_slave_mux

Bus/testbench/bus_slave_mux_tb.v
`timescale 1ns/100ps

`include "./Bus/bus_slave_mux.v"
`include "./Global/global_std_def.v"

module bus_slave_mux_tb;

    /*  slave 0  */
    reg s0_cs_n = `DISABLE_;
    reg [`WORD_DATA_BUS] s0_rd_data=`WORD_DATA_WIDTH'h0123;
    reg s0_rdy_n = `DISABLE_;
    /*  slave 1  */
    reg s1_cs_n = `DISABLE_;
    reg [`WORD_DATA_BUS] s1_rd_data=`WORD_DATA_WIDTH'h1234;
    reg s1_rdy_n = `ENABLE_;
    /*  slave 2  */
    reg s2_cs_n = `DISABLE_;
    reg [`WORD_DATA_BUS] s2_rd_data=`WORD_DATA_WIDTH'h2345;
    reg s2_rdy_n = `DISABLE_;
    /*  slave 3  */
    reg s3_cs_n = `DISABLE_;
    reg [`WORD_DATA_BUS] s3_rd_data=`WORD_DATA_WIDTH'h3456;
    reg s3_rdy_n = `ENABLE_;
    /*  slave 4  */
    reg s4_cs_n = `DISABLE_;
    reg [`WORD_DATA_BUS] s4_rd_data=`WORD_DATA_WIDTH'h4567;
    reg s4_rdy_n = `DISABLE_;
    /*  slave 5  */
    reg s5_cs_n = `DISABLE_;
    reg [`WORD_DATA_BUS] s5_rd_data=`WORD_DATA_WIDTH'h5678;
    reg s5_rdy_n = `ENABLE_;
    /*  slave 6  */
    reg s6_cs_n = `DISABLE_;
    reg [`WORD_DATA_BUS] s6_rd_data=`WORD_DATA_WIDTH'h6789;
    reg s6_rdy_n = `DISABLE_;
    /*  slave 7  */
    reg s7_cs_n = `DISABLE_;
    reg [`WORD_DATA_BUS] s7_rd_data=`WORD_DATA_WIDTH'h7890;
    reg s7_rdy_n = `ENABLE_;

    /*  master signal  */
    wire [`WORD_DATA_BUS] m_rd_data;
    wire m_rdy_n;
    
    bus_slave_mux bus_slave_mux_01(
        /*  slave 0  */
        s0_cs_n,
        s0_rd_data,
        s0_rdy_n,
        /*  slave 1  */
        s1_cs_n,
        s1_rd_data,
        s1_rdy_n,
        /*  slave 2  */
        s2_cs_n,
        s2_rd_data,
        s2_rdy_n,
        /*  slave 3  */
        s3_cs_n,
        s3_rd_data,
        s3_rdy_n,
        /*  slave 4  */
        s4_cs_n,
        s4_rd_data,
        s4_rdy_n,
        /*  slave 5  */
        s5_cs_n,
        s5_rd_data,
        s5_rdy_n,
        /*  slave 6  */
        s6_cs_n,
        s6_rd_data,
        s6_rdy_n,
        /*  slave 7  */
        s7_cs_n,
        s7_rd_data,
        s7_rdy_n,
        
        /*  master signal  */
        m_rd_data,
        m_rdy_n
    );

    /*  testbench  */
    initial
    begin
        $dumpfile("bus_slave_mux.vcd");
        $dumpvars(0,bus_slave_mux_tb);

        // s0
        #50 s0_cs_n = `ENABLE_;
        // s1
        #50 s0_cs_n = `DISABLE_;
        #50 s1_cs_n = `ENABLE_;
        // s2
        #50 s1_cs_n = `DISABLE_;
        #50 s2_cs_n = `ENABLE_;
        // s3
        #50 s2_cs_n = `DISABLE_;
        #50 s3_cs_n = `ENABLE_;
        // s4
        #50 s3_cs_n = `DISABLE_;
        #50 s4_cs_n = `ENABLE_;
        // s5
        #50 s4_cs_n = `DISABLE_;
        #50 s5_cs_n = `ENABLE_;
        // s6
        #50 s5_cs_n = `DISABLE_;
        #50 s6_cs_n = `ENABLE_;
        // s7
        #50 s6_cs_n = `DISABLE_;
        #50 s7_cs_n = `ENABLE_;
        // free
        #50 s7_cs_n = `DISABLE_;

        #100 $finish;
    end

endmodule // bus_slave_mux_tb

Bus/testbench/bus_slave_mux.vcd
$date
	Tue Nov 12 23:53:01 2019
$end
$version
	Icarus Verilog
$end
$timescale
	100ps
$end
$scope module bus_slave_mux_tb $end
$var wire 1 ! m_rdy_n $end
$var wire 32 " m_rd_data [31:0] $end
$var reg 1 # s0_cs_n $end
$var reg 32 $ s0_rd_data [31:0] $end
$var reg 1 % s0_rdy_n $end
$var reg 1 & s1_cs_n $end
$var reg 32 ' s1_rd_data [31:0] $end
$var reg 1 ( s1_rdy_n $end
$var reg 1 ) s2_cs_n $end
$var reg 32 * s2_rd_data [31:0] $end
$var reg 1 + s2_rdy_n $end
$var reg 1 , s3_cs_n $end
$var reg 32 - s3_rd_data [31:0] $end
$var reg 1 . s3_rdy_n $end
$var reg 1 / s4_cs_n $end
$var reg 32 0 s4_rd_data [31:0] $end
$var reg 1 1 s4_rdy_n $end
$var reg 1 2 s5_cs_n $end
$var reg 32 3 s5_rd_data [31:0] $end
$var reg 1 4 s5_rdy_n $end
$var reg 1 5 s6_cs_n $end
$var reg 32 6 s6_rd_data [31:0] $end
$var reg 1 7 s6_rdy_n $end
$var reg 1 8 s7_cs_n $end
$var reg 32 9 s7_rd_data [31:0] $end
$var reg 1 : s7_rdy_n $end
$scope module bus_slave_mux_01 $end
$var wire 1 # s0_cs_n $end
$var wire 32 ; s0_rd_data [31:0] $end
$var wire 1 % s0_rdy_n $end
$var wire 1 & s1_cs_n $end
$var wire 32 < s1_rd_data [31:0] $end
$var wire 1 ( s1_rdy_n $end
$var wire 1 ) s2_cs_n $end
$var wire 32 = s2_rd_data [31:0] $end
$var wire 1 + s2_rdy_n $end
$var wire 1 , s3_cs_n $end
$var wire 32 > s3_rd_data [31:0] $end
$var wire 1 . s3_rdy_n $end
$var wire 1 / s4_cs_n $end
$var wire 32 ? s4_rd_data [31:0] $end
$var wire 1 1 s4_rdy_n $end
$var wire 1 2 s5_cs_n $end
$var wire 32 @ s5_rd_data [31:0] $end
$var wire 1 4 s5_rdy_n $end
$var wire 1 5 s6_cs_n $end
$var wire 32 A s6_rd_data [31:0] $end
$var wire 1 7 s6_rdy_n $end
$var wire 1 8 s7_cs_n $end
$var wire 32 B s7_rd_data [31:0] $end
$var wire 1 : s7_rdy_n $end
$var reg 32 C m_rd_data [31:0] $end
$var reg 1 ! m_rdy_n $end
$upscope $end
$upscope $end
$enddefinitions $end
#0
$dumpvars
b0 C
b111100010010000 B
b110011110001001 A
b101011001111000 @
b100010101100111 ?
b11010001010110 >
b10001101000101 =
b1001000110100 <
b100100011 ;
0:
b111100010010000 9
18
17
b110011110001001 6
15
04
b101011001111000 3
12
11
b100010101100111 0
1/
0.
b11010001010110 -
1,
1+
b10001101000101 *
1)
0(
b1001000110100 '
1&
1%
b100100011 $
1#
b0 "
1!
$end
#500
b100100011 "
b100100011 C
0#
#1000
b0 "
b0 C
1#
#1500
0!
b1001000110100 "
b1001000110100 C
0&
#2000
1!
b0 "
b0 C
1&
#2500
b10001101000101 "
b10001101000101 C
0)
#3000
b0 "
b0 C
1)
#3500
0!
b11010001010110 "
b11010001010110 C
0,
#4000
1!
b0 "
b0 C
1,
#4500
b100010101100111 "
b100010101100111 C
0/
#5000
b0 "
b0 C
1/
#5500
0!
b101011001111000 "
b101011001111000 C
02
#6000
1!
b0 "
b0 C
12
#6500
b110011110001001 "
b110011110001001 C
05
#7000
b0 "
b0 C
15
#7500
0!
b111100010010000 "
b111100010010000 C
08
#8000
1!
b0 "
b0 C
18
