Global/global_std_def.v
`ifndef __GLOBAL_STD_DEF__
    `define __GLOBAL_STD_DEF__

    /*  singal level  */
    `define HIGH        1'b1
    `define LOW         1'b0

    /*  enable & disable  */
    `define DISABLE     1'b0
    `define ENABLE      1'b1
    `define DISABLE_    1'b1
    `define ENABLE_     1'b0

    /*  read & write  */
    `define READ        1'b1
    `define WRITE       1'b0

    /*  Least Significant Bit  */
    `define LSB         0

    /*  byte data  */
    `define BYTE_DATA_WIDTH     8
    `define BYTE_MSB            (`BYTE_DATA_WIDTH-1)
    `define BYTE_DATA_BUS       `BYTE_MSB:`LSB

    /*  word data  */
    `define WORD_DATA_WIDTH     32
    `define WORD_MSB            (`WORD_DATA_WIDTH-1)
    `define WORD_DATA_BUS       `WORD_MSB:`LSB

    /*  word address  */
    `define WORD_ADDR_WIDTH     30
    `define WORD_ADDR_MSB       (`WORD_ADDR_WIDTH-1)
    `define WORD_ADDR_BUS       `WORD_ADDR_MSB:`LSB

    /*  address offset  */
    `define BYTE_OFFSET_WIDTH   2
    `define BYTE_OFFSET_MSB     (`BYTE_OFFSET_WIDTH-1)
    `define BYTE_OFFSET_BUS     `BYTE_OFFSET_MSB:`LSB

    /*  address location  */
    `define WORD_ADDR_LOC       `WORD_ADDR_MSB:`BYTE_OFFSET_WIDTH
    `define BYTE_OFFSET_LOC     `BYTE_OFFSET_MSB:`LSB
    `define BYTE_OFFSET_WORD    2'b00

`endif

Bus/bus_def.v
`ifndef __BUS_DEF__
    `define __BUS_DEF__

    `include "./Global/global_std_def.v"

    /*  bus master num  */
    `define BUS_MASTER_CH           4
    `define BUS_MASTER_INDEX_WIDTH  2

    /*  bus master owner bus  */
    `define BUS_OWNER_BUS           (`BUS_MASTER_INDEX_WIDTH-1):`LSB

    /*  bus owner master  */
    `define BUS_OWNER_MASTER_0      2'h0
    `define BUS_OWNER_MASTER_1      2'h1
    `define BUS_OWNER_MASTER_2      2'h2
    `define BUS_OWNER_MASTER_3      2'h3

    /*  bus slave num  */
    `define BUS_SLAVE_CH            8
    `define BUS_SLAVE_INDEX_WIDTH   3

    /*  bus slave index bus  */
    `define BUS_SLAVE_INDEX_BUS     (`BUS_SLAVE_INDEX_WIDTH-1):`LSB
    /*  bus slave index map to address bus */
    `define BUS_SLAVE_INDEX_LOC     29:27

    /*  bus slave  */
    `define BUS_SLAVE_0     3'h0
    `define BUS_SLAVE_1     3'h1
    `define BUS_SLAVE_2     3'h2
    `define BUS_SLAVE_3     3'h3
    `define BUS_SLAVE_4     3'h4
    `define BUS_SLAVE_5     3'h5
    `define BUS_SLAVE_6     3'h6
    `define BUS_SLAVE_7     3'h7

`endif

Bus/bus_addr_dec.v
`include "./Bus/bus_def.v"
`include "./Global/global_std_def.v"

// book is wrong??? (p74,table:1-19,address)

module bus_addr_dec(
    /*  shared address bus  */
    input wire [`WORD_ADDR_BUS] s_addr,

    /*  chip select  */
    output reg s0_cs_n,
    output reg s1_cs_n,
    output reg s2_cs_n,
    output reg s3_cs_n,
    output reg s4_cs_n,
    output reg s5_cs_n,
    output reg s6_cs_n,
    output reg s7_cs_n
);
    /*  address index  */
    wire [`BUS_SLAVE_INDEX_BUS] s_index;

    assign s_index = s_addr[`BUS_SLAVE_INDEX_LOC];

    always @(*)
    begin
    
        s0_cs_n = `DISABLE_;
        s1_cs_n = `DISABLE_;
        s2_cs_n = `DISABLE_;
        s3_cs_n = `DISABLE_;
        s4_cs_n = `DISABLE_;
        s5_cs_n = `DISABLE_;
        s6_cs_n = `DISABLE_;
        s7_cs_n = `DISABLE_;

        case(s_index)
            `BUS_SLAVE_0: begin s0_cs_n = `ENABLE_; end
            `BUS_SLAVE_1: begin s1_cs_n = `ENABLE_; end
            `BUS_SLAVE_2: begin s2_cs_n = `ENABLE_; end
            `BUS_SLAVE_3: begin s3_cs_n = `ENABLE_; end
            `BUS_SLAVE_4: begin s4_cs_n = `ENABLE_; end
            `BUS_SLAVE_5: begin s5_cs_n = `ENABLE_; end
            `BUS_SLAVE_6: begin s6_cs_n = `ENABLE_; end
            `BUS_SLAVE_7: begin s7_cs_n = `ENABLE_; end
        endcase
    end

endmodule // bus_addr_dec

Bus/testbench/bus_addr_dec_tb.v
`timescale 1ns/100ps

`include "./Bus/bus_addr_dec.v"
`include "./Global/global_std_def.v"

module bus_addr_dec_tb;

    /*  shared address bus  */
    reg [`WORD_ADDR_BUS] s_addr;
    /*  chip select  */
    wire s0_cs_n;
    wire s1_cs_n;
    wire s2_cs_n;
    wire s3_cs_n;
    wire s4_cs_n;
    wire s5_cs_n;
    wire s6_cs_n;
    wire s7_cs_;

    bus_addr_dec bus_addr_dec_01(
        /*  shared address bus  */
        s_addr,

        /*  chip select  */
        s0_cs_n,
        s1_cs_n,
        s2_cs_n,
        s3_cs_n,
        s4_cs_n,
        s5_cs_n,
        s6_cs_n,
        s7_cs_n
    );


    /*  testbench  */
    initial
    begin
        $dumpfile("bus_addr_dec.vcd");
        $dumpvars(0,bus_addr_dec_tb);

        s_addr = `WORD_ADDR_WIDTH'h0000_0000;
        while (s_addr != `WORD_ADDR_WIDTH'h3F00_0000)
        begin
            #10 s_addr = s_addr + `WORD_ADDR_WIDTH'h0100_0000;
        end

        #100 $finish;
    end

endmodule // bus_addr_dec_tb

Bus/testbench/bus_addr_dec.vcd
$date
	Tue Nov 12 20:54:19 2019
$end
$version
	Icarus Verilog
$end
$timescale
	100ps
$end
$scope module bus_addr_dec_tb $end
$var wire 1 ! s7_cs_n $end
$var wire 1 " s6_cs_n $end
$var wire 1 # s5_cs_n $end
$var wire 1 $ s4_cs_n $end
$var wire 1 % s3_cs_n $end
$var wire 1 & s2_cs_n $end
$var wire 1 ' s1_cs_n $end
$var wire 1 ( s0_cs_n $end
$var reg 30 ) s_addr [29:0] $end
$scope module bus_addr_dec_01 $end
$var wire 30 * s_addr [29:0] $end
$var wire 3 + s_index [2:0] $end
$var reg 1 ( s0_cs_n $end
$var reg 1 ' s1_cs_n $end
$var reg 1 & s2_cs_n $end
$var reg 1 % s3_cs_n $end
$var reg 1 $ s4_cs_n $end
$var reg 1 # s5_cs_n $end
$var reg 1 " s6_cs_n $end
$var reg 1 ! s7_cs_n $end
$upscope $end
$upscope $end
$enddefinitions $end
#0
$dumpvars
b0 +
b0 *
b0 )
0(
1'
1&
1%
1$
1#
1"
1!
$end
#100
b1000000000000000000000000 )
b1000000000000000000000000 *
#200
b10000000000000000000000000 )
b10000000000000000000000000 *
#300
b11000000000000000000000000 )
b11000000000000000000000000 *
#400
b100000000000000000000000000 )
b100000000000000000000000000 *
#500
b101000000000000000000000000 )
b101000000000000000000000000 *
#600
b110000000000000000000000000 )
b110000000000000000000000000 *
#700
b111000000000000000000000000 )
b111000000000000000000000000 *
#800
0'
1(
b1 +
b1000000000000000000000000000 )
b1000000000000000000000000000 *
#900
b1001000000000000000000000000 )
b1001000000000000000000000000 *
#1000
b1010000000000000000000000000 )
b1010000000000000000000000000 *
#1100
b1011000000000000000000000000 )
b1011000000000000000000000000 *
#1200
b1100000000000000000000000000 )
b1100000000000000000000000000 *
#1300
b1101000000000000000000000000 )
b1101000000000000000000000000 *
#1400
b1110000000000000000000000000 )
b1110000000000000000000000000 *
#1500
b1111000000000000000000000000 )
b1111000000000000000000000000 *
#1600
0&
1'
b10 +
b10000000000000000000000000000 )
b10000000000000000000000000000 *
#1700
b10001000000000000000000000000 )
b10001000000000000000000000000 *
#1800
b10010000000000000000000000000 )
b10010000000000000000000000000 *
#1900
b10011000000000000000000000000 )
b10011000000000000000000000000 *
#2000
b10100000000000000000000000000 )
b10100000000000000000000000000 *
#2100
b10101000000000000000000000000 )
b10101000000000000000000000000 *
#2200
b10110000000000000000000000000 )
b10110000000000000000000000000 *
#2300
b10111000000000000000000000000 )
b10111000000000000000000000000 *
#2400
0%
1&
b11 +
b11000000000000000000000000000 )
b11000000000000000000000000000 *
#2500
b11001000000000000000000000000 )
b11001000000000000000000000000 *
#2600
b11010000000000000000000000000 )
b11010000000000000000000000000 *
#2700
b11011000000000000000000000000 )
b11011000000000000000000000000 *
#2800
b11100000000000000000000000000 )
b11100000000000000000000000000 *
#2900
b11101000000000000000000000000 )
b11101000000000000000000000000 *
#3000
b11110000000000000000000000000 )
b11110000000000000000000000000 *
#3100
b11111000000000000000000000000 )
b11111000000000000000000000000 *
#3200
0$
1%
b100 +
b100000000000000000000000000000 )
b100000000000000000000000000000 *
#3300
b100001000000000000000000000000 )
b100001000000000000000000000000 *
#3400
b100010000000000000000000000000 )
b100010000000000000000000000000 *
#3500
b100011000000000000000000000000 )
b100011000000000000000000000000 *
#3600
b100100000000000000000000000000 )
b100100000000000000000000000000 *
#3700
b100101000000000000000000000000 )
b100101000000000000000000000000 *
#3800
b100110000000000000000000000000 )
b100110000000000000000000000000 *
#3900
b100111000000000000000000000000 )
b100111000000000000000000000000 *
#4000
0#
1$
b101 +
b101000000000000000000000000000 )
b101000000000000000000000000000 *
#4100
b101001000000000000000000000000 )
b101001000000000000000000000000 *
#4200
b101010000000000000000000000000 )
b101010000000000000000000000000 *
#4300
b101011000000000000000000000000 )
b101011000000000000000000000000 *
#4400
b101100000000000000000000000000 )
b101100000000000000000000000000 *
#4500
b101101000000000000000000000000 )
b101101000000000000000000000000 *
#4600
b101110000000000000000000000000 )
b101110000000000000000000000000 *
#4700
b101111000000000000000000000000 )
b101111000000000000000000000000 *
#4800
0"
1#
b110 +
b110000000000000000000000000000 )
b110000000000000000000000000000 *
#4900
b110001000000000000000000000000 )
b110001000000000000000000000000 *
#5000
b110010000000000000000000000000 )
b110010000000000000000000000000 *
#5100
b110011000000000000000000000000 )
b110011000000000000000000000000 *
#5200
b110100000000000000000000000000 )
b110100000000000000000000000000 *
#5300
b110101000000000000000000000000 )
b110101000000000000000000000000 *
#5400
b110110000000000000000000000000 )
b110110000000000000000000000000 *
#5500
b110111000000000000000000000000 )
b110111000000000000000000000000 *
#5600
0!
1"
b111 +
b111000000000000000000000000000 )
b111000000000000000000000000000 *
#5700
b111001000000000000000000000000 )
b111001000000000000000000000000 *
#5800
b111010000000000000000000000000 )
b111010000000000000000000000000 *
#5900
b111011000000000000000000000000 )
b111011000000000000000000000000 *
#6000
b111100000000000000000000000000 )
b111100000000000000000000000000 *
#6100
b111101000000000000000000000000 )
b111101000000000000000000000000 *
#6200
b111110000000000000000000000000 )
b111110000000000000000000000000 *
#6300
b111111000000000000000000000000 )
b111111000000000000000000000000 *
