Global/global_std_def.v
`ifndef __GLOBAL_STD_DEF__
    `define __GLOBAL_STD_DEF__

    /*  singal level  */
    `define HIGH        1'b1
    `define LOW         1'b0

    /*  enable & disable  */
    `define DISABLE     1'b0
    `define ENABLE      1'b1
    `define DISABLE_    1'b1
    `define ENABLE_     1'b0

    /*  read & write  */
    `define READ        1'b1
    `define WRITE       1'b0

    /*  Least Significant Bit  */
    `define LSB         0

    /*  byte data  */
    `define BYTE_DATA_WIDTH     8
    `define BYTE_MSB            (`BYTE_DATA_WIDTH-1)
    `define BYTE_DATA_BUS       `BYTE_MSB:`LSB

    /*  word data  */
    `define WORD_DATA_WIDTH     32
    `define WORD_MSB            (`WORD_DATA_WIDTH-1)
    `define WORD_DATA_BUS       `WORD_MSB:`LSB

    /*  word address  */
    `define WORD_ADDR_WIDTH     30
    `define WORD_ADDR_MSB       (`WORD_ADDR_WIDTH-1)
    `define WORD_ADDR_BUS       `WORD_ADDR_MSB:`LSB

    /*  address offset  */
    `define BYTE_OFFSET_WIDTH   2
    `define BYTE_OFFSET_MSB     (`BYTE_OFFSET_WIDTH-1)
    `define BYTE_OFFSET_BUS     `BYTE_OFFSET_MSB:`LSB

    /*  address location  */
    `define WORD_ADDR_LOC       `WORD_ADDR_MSB:`BYTE_OFFSET_WIDTH
    `define BYTE_OFFSET_LOC     `BYTE_OFFSET_MSB:`LSB
    `define BYTE_OFFSET_WORD    2'b00

`endif

Global/global_cfg_def.v
`ifndef __GLOBAL_CFG_DEF__
    `define __GLOBAL_CFG_DEF__

    /*  choose RESET polarity  */
    // `define POSITIVE_RESET
    `define NEGATIVE_RESET

    /*  choose MEMORY polarity  */
    `define POSITIVE_MEMORY
    // `define NEGATIVE_MRMORY

    /*  Enable I/O Modules  */
    // `define IMPLEMENT_TIMER
    // `define IMPLEMENT_UART
    // `define IMPLEMENT_GPIO

    /*  generate RESET_ENABLE & RESET_DISABLE & RESET_EDGE */
    // book is wrong???
    // `ifdef POSITIVE_RESET
    //     `define RESET_EDGE      posedge
    //     `define RESET_ENABLE    1'b0
    //     `define RESET_DISABLE   1'b1
    // `elif NEGATIVE_RESET
        `define RESET_EDGE      negedge
        `define RESET_ENABLE    1'b1
        `define RESET_DISABLE   1'b0
    // `endif
    

    /*  generate MEM_ENABLE & MEM_DISABLE  */
    // `ifdef POSITIVE_MEMORY
        `define MEM_ENABLE    1'b1
        `define MEM_DISABLE   1'b0
    // `elif NEGATIVE_MRMORY
    //     `define MEM_ENABLE    1'b0
    //     `define MEM_DISABLE   1'b1
    // `endif

`endif

Bus/bus_def.v
`ifndef __BUS_DEF__
    `define __BUS_DEF__

    `include "./Global/global_std_def.v"

    /*  bus master num  */
    `define BUS_MASTER_CH           4
    `define BUS_MASTER_INDEX_WIDTH  2

    /*  bus master owner bus  */
    `define BUS_OWNER_BUS           (`BUS_MASTER_INDEX_WIDTH-1):`LSB

    /*  bus owner master  */
    `define BUS_OWNER_MASTER_0      2'h0
    `define BUS_OWNER_MASTER_1      2'h1
    `define BUS_OWNER_MASTER_2      2'h2
    `define BUS_OWNER_MASTER_3      2'h3

    /*  bus slave num  */
    `define BUS_SLAVE_CH            8
    `define BUS_SLAVE_INDEX_WIDTH   3

    /*  bus slave index bus  */
    `define BUS_SLAVE_INDEX_BUS     (`BUS_SLAVE_INDEX_WIDTH-1):`LSB
    /*  bus slave index map to address bus */
    `define BUS_SLAVE_INDEX_LOC     29:27

    /*  bus slave  */
    `define BUS_SLAVE_0     3'h0
    `define BUS_SLAVE_1     3'h1
    `define BUS_SLAVE_2     3'h2
    `define BUS_SLAVE_3     3'h3
    `define BUS_SLAVE_4     3'h4
    `define BUS_SLAVE_5     3'h5
    `define BUS_SLAVE_6     3'h6
    `define BUS_SLAVE_7     3'h7

`endif

Bus/bus_arbiter.v
`include "./Bus/bus_def.v"
`include "./Global/global_std_def.v"
`include "./Global/global_cfg_def.v"

module bus_arbiter(
    /*  clock & reset  */
    input wire clk,
    input wire reset,

    /*  bus master's request & grant buses */
    input wire m0_req_n,
    output reg m0_grnt_n,

    input wire m1_req_n,
    output reg m1_grnt_n,

    input wire m2_req_n,
    output reg m2_grnt_n,
    
    input wire m3_req_n,
    output reg m3_grnt_n
);

    reg [`BUS_OWNER_BUS] owner;

    /*  grant usage of bus  */
    always@(*)
    begin
        m0_grnt_n = `DISABLE_;
        m1_grnt_n = `DISABLE_;
        m2_grnt_n = `DISABLE_;
        m3_grnt_n = `DISABLE_;
        case (owner)
            `BUS_OWNER_MASTER_0: begin m0_grnt_n = `ENABLE_; end
            `BUS_OWNER_MASTER_1: begin m1_grnt_n = `ENABLE_; end
            `BUS_OWNER_MASTER_2: begin m2_grnt_n = `ENABLE_; end
            `BUS_OWNER_MASTER_3: begin m3_grnt_n = `ENABLE_; end
        endcase
    end

    /*  arbiter of usage of bus  */
    always@(posedge clk or `RESET_EDGE reset)
    begin
        if (reset == `RESET_DISABLE)    // book is wrong ???
        begin
            /*  reset  */
            owner <= #1 `BUS_OWNER_MASTER_0;
        end
        else
        begin
            /*  arbiter polling  */
            case (owner)
                `BUS_OWNER_MASTER_0:
                begin
                    if (m0_req_n == `ENABLE_)
                    begin
                        owner <= #1 `BUS_OWNER_MASTER_0;
                    end
                    else if(m1_req_n == `ENABLE_)
                    begin
                        owner <= #1 `BUS_OWNER_MASTER_1;
                    end
                    else if(m2_req_n == `ENABLE_)
                    begin
                        owner <= #1 `BUS_OWNER_MASTER_2;
                    end
                    else if(m3_req_n == `ENABLE_)
                    begin
                        owner <= #1 `BUS_OWNER_MASTER_3;
                    end
                end

                `BUS_OWNER_MASTER_1:
                begin
                    if (m1_req_n == `ENABLE_)
                    begin
                        owner <= #1 `BUS_OWNER_MASTER_1;
                    end
                    else if(m2_req_n == `ENABLE_)
                    begin
                        owner <= #1 `BUS_OWNER_MASTER_2;
                    end
                    else if(m3_req_n == `ENABLE_)
                    begin
                        owner <= #1 `BUS_OWNER_MASTER_3;
                    end
                    else if(m0_req_n == `ENABLE_)
                    begin
                        owner <= #1 `BUS_OWNER_MASTER_0;
                    end
                end

                `BUS_OWNER_MASTER_2:
                begin
                    if (m2_req_n == `ENABLE_)
                    begin
                        owner <= #1 `BUS_OWNER_MASTER_2;
                    end
                    else if(m3_req_n == `ENABLE_)
                    begin
                        owner <= #1 `BUS_OWNER_MASTER_3;
                    end
                    else if(m0_req_n == `ENABLE_)
                    begin
                        owner <= #1 `BUS_OWNER_MASTER_0;
                    end
                    else if(m1_req_n == `ENABLE_)
                    begin
                        owner <= #1 `BUS_OWNER_MASTER_1;
                    end
                end

                `BUS_OWNER_MASTER_3:
                begin
                    if (m3_req_n == `ENABLE_)
                    begin
                        owner <= #1 `BUS_OWNER_MASTER_3;
                    end
                    else if(m0_req_n == `ENABLE_)
                    begin
                        owner <= #1 `BUS_OWNER_MASTER_0;
                    end
                    else if(m1_req_n == `ENABLE_)
                    begin
                        owner <= #1 `BUS_OWNER_MASTER_1;
                    end
                    else if(m2_req_n == `ENABLE_)
                    begin
                        owner <= #1 `BUS_OWNER_MASTER_2;
                    end
                end
            endcase
        end

    end
endmodule // bus_arbiterf

Bus/testbench/bus_arbiter_tb.v
`timescale 1ns/100ps

`include "./Bus/bus_arbiter.v"
`include "./Global/global_std_def.v"

module bus_arbiter_tb;

    /*  clock & reset  */
    reg clk = `LOW;
    reg reset = `RESET_DISABLE;

    /*  bus master's request & grant buses */
    reg m0_req_n = `DISABLE_;
    wire m0_grnt_n;

    reg m1_req_n = `DISABLE_;
    wire m1_grnt_n;

    reg m2_req_n = `DISABLE_;
    wire m2_grnt_n;
    
    reg m3_req_n = `DISABLE_;
    wire m3_grnt_n;

    /*  Instance  */
    bus_arbiter bus_arbiter_01(

        /*  clock & reset  */
        clk,
        reset,

        /*  bus master's request & grant buses */
        m0_req_n,
        m0_grnt_n,

        m1_req_n,
        m1_grnt_n,

        m2_req_n,
        m2_grnt_n,

        m3_req_n,
        m3_grnt_n
    );

    /*  clock  */
    always
        #10 clk = ~clk;

    /*  testbench  */
    initial
    begin
        $dumpfile("bus_arbiter.vcd");
        $dumpvars(0,bus_arbiter_tb);

        // test for reset
        #50 reset = `RESET_ENABLE;
        #50 m3_req_n = `ENABLE_;
        #50 reset = `RESET_DISABLE;
        #50 m3_req_n = `DISABLE_;
        #50 reset = `RESET_ENABLE;


        // m0 request usage of bus
        #100 m0_req_n = `ENABLE_;

        // when m0 using bus, m1 request
        #50 m1_req_n = `ENABLE_;

        // m0 request finished, m1 will use the bus
        #50 m0_req_n = `DISABLE_;

        // when m1 using, m2 & m3 request
        #30 m3_req_n = `ENABLE_;
        #30 m2_req_n = `ENABLE_;

        // m1 request finished, m2 will use the bus
        #30 m1_req_n = `DISABLE_;

        // m2 request finished, m3 will use the bus
        #50 m2_req_n = `DISABLE_;

        // m3 requested finished, bus is available
        #50 m3_req_n = `DISABLE_;

        #100 $finish;
    end

endmodule // bus_arbiter_tb

Bus/testbench/bus_arbiter.vcd
$date
	Mon Nov 11 20:43:24 2019
$end
$version
	Icarus Verilog
$end
$timescale
	100ps
$end
$scope module bus_arbiter_tb $end
$var wire 1 ! m3_grnt_n $end
$var wire 1 " m2_grnt_n $end
$var wire 1 # m1_grnt_n $end
$var wire 1 $ m0_grnt_n $end
$var reg 1 % clk $end
$var reg 1 & m0_req_n $end
$var reg 1 ' m1_req_n $end
$var reg 1 ( m2_req_n $end
$var reg 1 ) m3_req_n $end
$var reg 1 * reset $end
$scope module bus_arbiter_01 $end
$var wire 1 % clk $end
$var wire 1 & m0_req_n $end
$var wire 1 ' m1_req_n $end
$var wire 1 ( m2_req_n $end
$var wire 1 ) m3_req_n $end
$var wire 1 * reset $end
$var reg 1 $ m0_grnt_n $end
$var reg 1 # m1_grnt_n $end
$var reg 1 " m2_grnt_n $end
$var reg 1 ! m3_grnt_n $end
$var reg 2 + owner [1:0] $end
$upscope $end
$upscope $end
$enddefinitions $end
#0
$dumpvars
bx +
1*
1)
1(
1'
1&
0%
x$
x#
x"
x!
$end
#100
1%
#110
1!
1"
1#
0$
b0 +
#200
0%
#300
1%
#400
0%
#500
1%
0*
#600
0%
#700
1%
#800
0%
#900
1%
#1000
0%
0)
#1100
1%
#1110
0!
1$
b11 +
#1200
0%
#1300
1%
#1400
0%
#1500
1%
1*
#1510
0$
1!
b0 +
#1600
0%
#1700
1%
#1800
0%
#1900
1%
#2000
0%
1)
#2100
1%
#2200
0%
#2300
1%
#2400
0%
#2500
1%
0*
#2600
0%
#2700
1%
#2800
0%
#2900
1%
#3000
0%
#3100
1%
#3200
0%
#3300
1%
#3400
0%
#3500
1%
0&
#3600
0%
#3700
1%
#3800
0%
#3900
1%
#4000
0%
0'
#4100
1%
#4200
0%
#4300
1%
#4400
0%
#4500
1%
1&
#4510
0#
1$
b1 +
#4600
0%
#4700
1%
#4800
0%
0)
#4900
1%
#5000
0%
#5100
1%
0(
#5200
0%
#5300
1%
#5400
0%
1'
#5500
1%
#5510
0"
1#
b10 +
#5600
0%
#5700
1%
#5800
0%
#5900
1%
1(
#5910
0!
1"
b11 +
#6000
0%
#6100
1%
#6200
0%
#6300
1%
#6400
0%
1)
